Workbook

Sheet サマリー
A1: AIエージェント／MCP × 生産性向上・生産管理・営業効率化 セミナー調査（第2版：プラットフォーム巡回）
A2: 対象期間: 2026/07/01〜2026/09/30（調査日 2026/09/30）
A4: テーマ分類 | B4: 件数 | C4: 開催回数計 | D4: 集客数判明 | E4: 参加・申込・来場の合計 | F4: 7月 | G4: 8月 | H4: 9月
A5: 生産性向上・業務効率化 | B5: =COUNTIF('セミナー一覧'!$M$2:$M$685,A5) | C5: =SUMIFS('セミナー一覧'!$E$2:$E$685,'セミナー一覧'!$M$2:$M$685,A5) | D5: =COUNTIFS('セミナー一覧'!$M$2:$M$685,A5,'セミナー一覧'!$P$2:$P$685,">0") | E5: =SUMIFS('セミナー一覧'!$P$2:$P$685,'セミナー一覧'!$M$2:$M$685,A5,'セミナー一覧'!$Q$2:$Q$685,"<>定員",'セミナー一覧'!$Q$2:$Q$685,"<>予定来場者数") | F5: =COUNTIFS('セミナー一覧'!$M$2:$M$685,A5,'セミナー一覧'!$D$2:$D$685,"7月") | G5: =COUNTIFS('セミナー一覧'!$M$2:$M$685,A5,'セミナー一覧'!$D$2:$D$685,"8月") | H5: =COUNTIFS('セミナー一覧'!$M$2:$M$685,A5,'セミナー一覧'!$D$2:$D$685,"9月")
A6: 営業・マーケ・CS | B6: =COUNTIF('セミナー一覧'!$M$2:$M$685,A6) | C6: =SUMIFS('セミナー一覧'!$E$2:$E$685,'セミナー一覧'!$M$2:$M$685,A6) | D6: =COUNTIFS('セミナー一覧'!$M$2:$M$685,A6,'セミナー一覧'!$P$2:$P$685,">0") | E6: =SUMIFS('セミナー一覧'!$P$2:$P$685,'セミナー一覧'!$M$2:$M$685,A6,'セミナー一覧'!$Q$2:$Q$685,"<>定員",'セミナー一覧'!$Q$2:$Q$685,"<>予定来場者数") | F6: =COUNTIFS('セミナー一覧'!$M$2:$M$685,A6,'セミナー一覧'!$D$2:$D$685,"7月") | G6: =COUNTIFS('セミナー一覧'!$M$2:$M$685,A6,'セミナー一覧'!$D$2:$D$685,"8月") | H6: =COUNTIFS('セミナー一覧'!$M$2:$M$685,A6,'セミナー一覧'!$D$2:$D$685,"9月")
A7: 生産管理・製造・SCM | B7: =COUNTIF('セミナー一覧'!$M$2:$M$685,A7) | C7: =SUMIFS('セミナー一覧'!$E$2:$E$685,'セミナー一覧'!$M$2:$M$685,A7) | D7: =COUNTIFS('セミナー一覧'!$M$2:$M$685,A7,'セミナー一覧'!$P$2:$P$685,">0") | E7: =SUMIFS('セミナー一覧'!$P$2:$P$685,'セミナー一覧'!$M$2:$M$685,A7,'セミナー一覧'!$Q$2:$Q$685,"<>定員",'セミナー一覧'!$Q$2:$Q$685,"<>予定来場者数") | F7: =COUNTIFS('セミナー一覧'!$M$2:$M$685,A7,'セミナー一覧'!$D$2:$D$685,"7月") | G7: =COUNTIFS('セミナー一覧'!$M$2:$M$685,A7,'セミナー一覧'!$D$2:$D$685,"8月") | H7: =COUNTIFS('セミナー一覧'!$M$2:$M$685,A7,'セミナー一覧'!$D$2:$D$685,"9月")
A8: 大型カンファレンス・展示会 | B8: =COUNTIF('セミナー一覧'!$M$2:$M$685,A8) | C8: =SUMIFS('セミナー一覧'!$E$2:$E$685,'セミナー一覧'!$M$2:$M$685,A8) | D8: =COUNTIFS('セミナー一覧'!$M$2:$M$685,A8,'セミナー一覧'!$P$2:$P$685,">0") | E8: =SUMIFS('セミナー一覧'!$P$2:$P$685,'セミナー一覧'!$M$2:$M$685,A8,'セミナー一覧'!$Q$2:$Q$685,"<>定員",'セミナー一覧'!$Q$2:$Q$685,"<>予定来場者数") | F8: =COUNTIFS('セミナー一覧'!$M$2:$M$685,A8,'セミナー一覧'!$D$2:$D$685,"7月") | G8: =COUNTIFS('セミナー一覧'!$M$2:$M$685,A8,'セミナー一覧'!$D$2:$D$685,"8月") | H8: =COUNTIFS('セミナー一覧'!$M$2:$M$685,A8,'セミナー一覧'!$D$2:$D$685,"9月")
A9: 開発生産性 | B9: =COUNTIF('セミナー一覧'!$M$2:$M$685,A9) | C9: =SUMIFS('セミナー一覧'!$E$2:$E$685,'セミナー一覧'!$M$2:$M$685,A9) | D9: =COUNTIFS('セミナー一覧'!$M$2:$M$685,A9,'セミナー一覧'!$P$2:$P$685,">0") | E9: =SUMIFS('セミナー一覧'!$P$2:$P$685,'セミナー一覧'!$M$2:$M$685,A9,'セミナー一覧'!$Q$2:$Q$685,"<>定員",'セミナー一覧'!$Q$2:$Q$685,"<>予定来場者数") | F9: =COUNTIFS('セミナー一覧'!$M$2:$M$685,A9,'セミナー一覧'!$D$2:$D$685,"7月") | G9: =COUNTIFS('セミナー一覧'!$M$2:$M$685,A9,'セミナー一覧'!$D$2:$D$685,"8月") | H9: =COUNTIFS('セミナー一覧'!$M$2:$M$685,A9,'セミナー一覧'!$D$2:$D$685,"9月")
A10: 技術・AI全般 | B10: =COUNTIF('セミナー一覧'!$M$2:$M$685,A10) | C10: =SUMIFS('セミナー一覧'!$E$2:$E$685,'セミナー一覧'!$M$2:$M$685,A10) | D10: =COUNTIFS('セミナー一覧'!$M$2:$M$685,A10,'セミナー一覧'!$P$2:$P$685,">0") | E10: =SUMIFS('セミナー一覧'!$P$2:$P$685,'セミナー一覧'!$M$2:$M$685,A10,'セミナー一覧'!$Q$2:$Q$685,"<>定員",'セミナー一覧'!$Q$2:$Q$685,"<>予定来場者数") | F10: =COUNTIFS('セミナー一覧'!$M$2:$M$685,A10,'セミナー一覧'!$D$2:$D$685,"7月") | G10: =COUNTIFS('セミナー一覧'!$M$2:$M$685,A10,'セミナー一覧'!$D$2:$D$685,"8月") | H10: =COUNTIFS('セミナー一覧'!$M$2:$M$685,A10,'セミナー一覧'!$D$2:$D$685,"9月")
A11: 合計 | B11: =SUM(B5:B10) | C11: =SUM(C5:C10) | D11: =SUM(D5:D10) | E11: =SUM(E5:E10) | F11: =SUM(F5:F10) | G11: =SUM(G5:G10) | H11: =SUM(H5:H10)
A13: 掲載プラットフォーム | B13: 件数 | C13: 開催回数計 | D13: 集客数判明 | E13: 参加・申込・来場の合計 | F13: 7月 | G13: 8月 | H13: 9月
A14: connpass | B14: =COUNTIF('セミナー一覧'!$J$2:$J$685,A14) | C14: =SUMIFS('セミナー一覧'!$E$2:$E$685,'セミナー一覧'!$J$2:$J$685,A14) | D14: =COUNTIFS('セミナー一覧'!$J$2:$J$685,A14,'セミナー一覧'!$P$2:$P$685,">0") | E14: =SUMIFS('セミナー一覧'!$P$2:$P$685,'セミナー一覧'!$J$2:$J$685,A14,'セミナー一覧'!$Q$2:$Q$685,"<>定員",'セミナー一覧'!$Q$2:$Q$685,"<>予定来場者数") | F14: =COUNTIFS('セミナー一覧'!$J$2:$J$685,A14,'セミナー一覧'!$D$2:$D$685,"7月") | G14: =COUNTIFS('セミナー一覧'!$J$2:$J$685,A14,'セミナー一覧'!$D$2:$D$685,"8月") | H14: =COUNTIFS('セミナー一覧'!$J$2:$J$685,A14,'セミナー一覧'!$D$2:$D$685,"9月")
A15: TECH PLAY | B15: =COUNTIF('セミナー一覧'!$J$2:$J$685,A15) | C15: =SUMIFS('セミナー一覧'!$E$2:$E$685,'セミナー一覧'!$J$2:$J$685,A15) | D15: =COUNTIFS('セミナー一覧'!$J$2:$J$685,A15,'セミナー一覧'!$P$2:$P$685,">0") | E15: =SUMIFS('セミナー一覧'!$P$2:$P$685,'セミナー一覧'!$J$2:$J$685,A15,'セミナー一覧'!$Q$2:$Q$685,"<>定員",'セミナー一覧'!$Q$2:$Q$685,"<>予定来場者数") | F15: =COUNTIFS('セミナー一覧'!$J$2:$J$685,A15,'セミナー一覧'!$D$2:$D$685,"7月") | G15: =COUNTIFS('セミナー一覧'!$J$2:$J$685,A15,'セミナー一覧'!$D$2:$D$685,"8月") | H15: =COUNTIFS('セミナー一覧'!$J$2:$J$685,A15,'セミナー一覧'!$D$2:$D$685,"9月")
A16: こくちーずプロ | B16: =COUNTIF('セミナー一覧'!$J$2:$J$685,A16) | C16: =SUMIFS('セミナー一覧'!$E$2:$E$685,'セミナー一覧'!$J$2:$J$685,A16) | D16: =COUNTIFS('セミナー一覧'!$J$2:$J$685,A16,'セミナー一覧'!$P$2:$P$685,">0") | E16: =SUMIFS('セミナー一覧'!$P$2:$P$685,'セミナー一覧'!$J$2:$J$685,A16,'セミナー一覧'!$Q$2:$Q$685,"<>定員",'セミナー一覧'!$Q$2:$Q$685,"<>予定来場者数") | F16: =COUNTIFS('セミナー一覧'!$J$2:$J$685,A16,'セミナー一覧'!$D$2:$D$685,"7月") | G16: =COUNTIFS('セミナー一覧'!$J$2:$J$685,A16,'セミナー一覧'!$D$2:$D$685,"8月") | H16: =COUNTIFS('セミナー一覧'!$J$2:$J$685,A16,'セミナー一覧'!$D$2:$D$685,"9月")
A17: Doorkeeper | B17: =COUNTIF('セミナー一覧'!$J$2:$J$685,A17) | C17: =SUMIFS('セミナー一覧'!$E$2:$E$685,'セミナー一覧'!$J$2:$J$685,A17) | D17: =COUNTIFS('セミナー一覧'!$J$2:$J$685,A17,'セミナー一覧'!$P$2:$P$685,">0") | E17: =SUMIFS('セミナー一覧'!$P$2:$P$685,'セミナー一覧'!$J$2:$J$685,A17,'セミナー一覧'!$Q$2:$Q$685,"<>定員",'セミナー一覧'!$Q$2:$Q$685,"<>予定来場者数") | F17: =COUNTIFS('セミナー一覧'!$J$2:$J$685,A17,'セミナー一覧'!$D$2:$D$685,"7月") | G17: =COUNTIFS('セミナー一覧'!$J$2:$J$685,A17,'セミナー一覧'!$D$2:$D$685,"8月") | H17: =COUNTIFS('セミナー一覧'!$J$2:$J$685,A17,'セミナー一覧'!$D$2:$D$685,"9月")
A18: 個別調査（公式サイト・PR TIMES等） | B18: =COUNTIF('セミナー一覧'!$J$2:$J$685,A18) | C18: =SUMIFS('セミナー一覧'!$E$2:$E$685,'セミナー一覧'!$J$2:$J$685,A18) | D18: =COUNTIFS('セミナー一覧'!$J$2:$J$685,A18,'セミナー一覧'!$P$2:$P$685,">0") | E18: =SUMIFS('セミナー一覧'!$P$2:$P$685,'セミナー一覧'!$J$2:$J$685,A18,'セミナー一覧'!$Q$2:$Q$685,"<>定員",'セミナー一覧'!$Q$2:$Q$685,"<>予定来場者数") | F18: =COUNTIFS('セミナー一覧'!$J$2:$J$685,A18,'セミナー一覧'!$D$2:$D$685,"7月") | G18: =COUNTIFS('セミナー一覧'!$J$2:$J$685,A18,'セミナー一覧'!$D$2:$D$685,"8月") | H18: =COUNTIFS('セミナー一覧'!$J$2:$J$685,A18,'セミナー一覧'!$D$2:$D$685,"9月")
A19: PR TIMES | B19: =COUNTIF('セミナー一覧'!$J$2:$J$685,A19) | C19: =SUMIFS('セミナー一覧'!$E$2:$E$685,'セミナー一覧'!$J$2:$J$685,A19) | D19: =COUNTIFS('セミナー一覧'!$J$2:$J$685,A19,'セミナー一覧'!$P$2:$P$685,">0") | E19: =SUMIFS('セミナー一覧'!$P$2:$P$685,'セミナー一覧'!$J$2:$J$685,A19,'セミナー一覧'!$Q$2:$Q$685,"<>定員",'セミナー一覧'!$Q$2:$Q$685,"<>予定来場者数") | F19: =COUNTIFS('セミナー一覧'!$J$2:$J$685,A19,'セミナー一覧'!$D$2:$D$685,"7月") | G19: =COUNTIFS('セミナー一覧'!$J$2:$J$685,A19,'セミナー一覧'!$D$2:$D$685,"8月") | H19: =COUNTIFS('セミナー一覧'!$J$2:$J$685,A19,'セミナー一覧'!$D$2:$D$685,"9月")
A20: ビジネス+IT | B20: =COUNTIF('セミナー一覧'!$J$2:$J$685,A20) | C20: =SUMIFS('セミナー一覧'!$E$2:$E$685,'セミナー一覧'!$J$2:$J$685,A20) | D20: =COUNTIFS('セミナー一覧'!$J$2:$J$685,A20,'セミナー一覧'!$P$2:$P$685,">0") | E20: =SUMIFS('セミナー一覧'!$P$2:$P$685,'セミナー一覧'!$J$2:$J$685,A20,'セミナー一覧'!$Q$2:$Q$685,"<>定員",'セミナー一覧'!$Q$2:$Q$685,"<>予定来場者数") | F20: =COUNTIFS('セミナー一覧'!$J$2:$J$685,A20,'セミナー一覧'!$D$2:$D$685,"7月") | G20: =COUNTIFS('セミナー一覧'!$J$2:$J$685,A20,'セミナー一覧'!$D$2:$D$685,"8月") | H20: =COUNTIFS('セミナー一覧'!$J$2:$J$685,A20,'セミナー一覧'!$D$2:$D$685,"9月")
A21: Peatix | B21: =COUNTIF('セミナー一覧'!$J$2:$J$685,A21) | C21: =SUMIFS('セミナー一覧'!$E$2:$E$685,'セミナー一覧'!$J$2:$J$685,A21) | D21: =COUNTIFS('セミナー一覧'!$J$2:$J$685,A21,'セミナー一覧'!$P$2:$P$685,">0") | E21: =SUMIFS('セミナー一覧'!$P$2:$P$685,'セミナー一覧'!$J$2:$J$685,A21,'セミナー一覧'!$Q$2:$Q$685,"<>定員",'セミナー一覧'!$Q$2:$Q$685,"<>予定来場者数") | F21: =COUNTIFS('セミナー一覧'!$J$2:$J$685,A21,'セミナー一覧'!$D$2:$D$685,"7月") | G21: =COUNTIFS('セミナー一覧'!$J$2:$J$685,A21,'セミナー一覧'!$D$2:$D$685,"8月") | H21: =COUNTIFS('セミナー一覧'!$J$2:$J$685,A21,'セミナー一覧'!$D$2:$D$685,"9月")
A22: ZDNET Japan イベント | B22: =COUNTIF('セミナー一覧'!$J$2:$J$685,A22) | C22: =SUMIFS('セミナー一覧'!$E$2:$E$685,'セミナー一覧'!$J$2:$J$685,A22) | D22: =COUNTIFS('セミナー一覧'!$J$2:$J$685,A22,'セミナー一覧'!$P$2:$P$685,">0") | E22: =SUMIFS('セミナー一覧'!$P$2:$P$685,'セミナー一覧'!$J$2:$J$685,A22,'セミナー一覧'!$Q$2:$Q$685,"<>定員",'セミナー一覧'!$Q$2:$Q$685,"<>予定来場者数") | F22: =COUNTIFS('セミナー一覧'!$J$2:$J$685,A22,'セミナー一覧'!$D$2:$D$685,"7月") | G22: =COUNTIFS('セミナー一覧'!$J$2:$J$685,A22,'セミナー一覧'!$D$2:$D$685,"8月") | H22: =COUNTIFS('セミナー一覧'!$J$2:$J$685,A22,'セミナー一覧'!$D$2:$D$685,"9月")
A23: マジセミ | B23: =COUNTIF('セミナー一覧'!$J$2:$J$685,A23) | C23: =SUMIFS('セミナー一覧'!$E$2:$E$685,'セミナー一覧'!$J$2:$J$685,A23) | D23: =COUNTIFS('セミナー一覧'!$J$2:$J$685,A23,'セミナー一覧'!$P$2:$P$685,">0") | E23: =SUMIFS('セミナー一覧'!$P$2:$P$685,'セミナー一覧'!$J$2:$J$685,A23,'セミナー一覧'!$Q$2:$Q$685,"<>定員",'セミナー一覧'!$Q$2:$Q$685,"<>予定来場者数") | F23: =COUNTIFS('セミナー一覧'!$J$2:$J$685,A23,'セミナー一覧'!$D$2:$D$685,"7月") | G23: =COUNTIFS('セミナー一覧'!$J$2:$J$685,A23,'セミナー一覧'!$D$2:$D$685,"8月") | H23: =COUNTIFS('セミナー一覧'!$J$2:$J$685,A23,'セミナー一覧'!$D$2:$D$685,"9月")
A24: セミナー情報.com | B24: =COUNTIF('セミナー一覧'!$J$2:$J$685,A24) | C24: =SUMIFS('セミナー一覧'!$E$2:$E$685,'セミナー一覧'!$J$2:$J$685,A24) | D24: =COUNTIFS('セミナー一覧'!$J$2:$J$685,A24,'セミナー一覧'!$P$2:$P$685,">0") | E24: =SUMIFS('セミナー一覧'!$P$2:$P$685,'セミナー一覧'!$J$2:$J$685,A24,'セミナー一覧'!$Q$2:$Q$685,"<>定員",'セミナー一覧'!$Q$2:$Q$685,"<>予定来場者数") | F24: =COUNTIFS('セミナー一覧'!$J$2:$J$685,A24,'セミナー一覧'!$D$2:$D$685,"7月") | G24: =COUNTIFS('セミナー一覧'!$J$2:$J$685,A24,'セミナー一覧'!$D$2:$D$685,"8月") | H24: =COUNTIFS('セミナー一覧'!$J$2:$J$685,A24,'セミナー一覧'!$D$2:$D$685,"9月")
A25: 日経イベント | B25: =COUNTIF('セミナー一覧'!$J$2:$J$685,A25) | C25: =SUMIFS('セミナー一覧'!$E$2:$E$685,'セミナー一覧'!$J$2:$J$685,A25) | D25: =COUNTIFS('セミナー一覧'!$J$2:$J$685,A25,'セミナー一覧'!$P$2:$P$685,">0") | E25: =SUMIFS('セミナー一覧'!$P$2:$P$685,'セミナー一覧'!$J$2:$J$685,A25,'セミナー一覧'!$Q$2:$Q$685,"<>定員",'セミナー一覧'!$Q$2:$Q$685,"<>予定来場者数") | F25: =COUNTIFS('セミナー一覧'!$J$2:$J$685,A25,'セミナー一覧'!$D$2:$D$685,"7月") | G25: =COUNTIFS('セミナー一覧'!$J$2:$J$685,A25,'セミナー一覧'!$D$2:$D$685,"8月") | H25: =COUNTIFS('セミナー一覧'!$J$2:$J$685,A25,'セミナー一覧'!$D$2:$D$685,"9月")
... A28: Salesforce 公式 | B28: =COUNTIF('セミナー一覧'!$J$2:$J$685,A28) | C28: =SUMIFS('セミナー一覧'!$E$2:$E$685,'セミナー一覧'!$J$2:$J$685,A28) | D28: =COUNTIFS('セミナー一覧'!$J$2:$J$685,A28,'セミナー一覧'!$P$2:$P$685,">0") | E28: =SUMIFS('セミナー一覧'!$P$2:$P$685,'セミナー一覧'!$J$2:$J$685,A28,'セミナー一覧'!$Q$2:$Q$685,"<>定員",'セミナー一覧'!$Q$2:$Q$685,"<>予定来場者数") | F28: =COUNTIFS('セミナー一覧'!$J$2:$J$685,A28,'セミナー一覧'!$D$2:$D$685,"7月") | G28: =COUNTIFS('セミナー一覧'!$J$2:$J$685,A28,'セミナー一覧'!$D$2:$D$685,"8月") | H28: =COUNTIFS('セミナー一覧'!$J$2:$J$685,A28,'セミナー一覧'!$D$2:$D$685,"9月")
A29: 合計 | B29: =SUM(B14:B28) | C29: =SUM(C14:C28) | D29: =SUM(D14:D28) | E29: =SUM(E14:E28) | F29: =SUM(F14:F28) | G29: =SUM(G14:G28) | H29: =SUM(H14:H28)
A31: 関連度 | B31: 件数 | C31: 開催回数計 | D31: 集客数判明 | E31: 参加・申込・来場の合計 | F31: 7月 | G31: 8月 | H31: 9月
A32: ◎ | B32: =COUNTIF('セミナー一覧'!$O$2:$O$685,A32) | C32: =SUMIFS('セミナー一覧'!$E$2:$E$685,'セミナー一覧'!$O$2:$O$685,A32) | D32: =COUNTIFS('セミナー一覧'!$O$2:$O$685,A32,'セミナー一覧'!$P$2:$P$685,">0") | E32: =SUMIFS('セミナー一覧'!$P$2:$P$685,'セミナー一覧'!$O$2:$O$685,A32,'セミナー一覧'!$Q$2:$Q$685,"<>定員",'セミナー一覧'!$Q$2:$Q$685,"<>予定来場者数") | F32: =COUNTIFS('セミナー一覧'!$O$2:$O$685,A32,'セミナー一覧'!$D$2:$D$685,"7月") | G32: =COUNTIFS('セミナー一覧'!$O$2:$O$685,A32,'セミナー一覧'!$D$2:$D$685,"8月") | H32: =COUNTIFS('セミナー一覧'!$O$2:$O$685,A32,'セミナー一覧'!$D$2:$D$685,"9月")
A33: ○ | B33: =COUNTIF('セミナー一覧'!$O$2:$O$685,A33) | C33: =SUMIFS('セミナー一覧'!$E$2:$E$685,'セミナー一覧'!$O$2:$O$685,A33) | D33: =COUNTIFS('セミナー一覧'!$O$2:$O$685,A33,'セミナー一覧'!$P$2:$P$685,">0") | E33: =SUMIFS('セミナー一覧'!$P$2:$P$685,'セミナー一覧'!$O$2:$O$685,A33,'セミナー一覧'!$Q$2:$Q$685,"<>定員",'セミナー一覧'!$Q$2:$Q$685,"<>予定来場者数") | F33: =COUNTIFS('セミナー一覧'!$O$2:$O$685,A33,'セミナー一覧'!$D$2:$D$685,"7月") | G33: =COUNTIFS('セミナー一覧'!$O$2:$O$685,A33,'セミナー一覧'!$D$2:$D$685,"8月") | H33: =COUNTIFS('セミナー一覧'!$O$2:$O$685,A33,'セミナー一覧'!$D$2:$D$685,"9月")
A34: △ | B34: =COUNTIF('セミナー一覧'!$O$2:$O$685,A34) | C34: =SUMIFS('セミナー一覧'!$E$2:$E$685,'セミナー一覧'!$O$2:$O$685,A34) | D34: =COUNTIFS('セミナー一覧'!$O$2:$O$685,A34,'セミナー一覧'!$P$2:$P$685,">0") | E34: =SUMIFS('セミナー一覧'!$P$2:$P$685,'セミナー一覧'!$O$2:$O$685,A34,'セミナー一覧'!$Q$2:$Q$685,"<>定員",'セミナー一覧'!$Q$2:$Q$685,"<>予定来場者数") | F34: =COUNTIFS('セミナー一覧'!$O$2:$O$685,A34,'セミナー一覧'!$D$2:$D$685,"7月") | G34: =COUNTIFS('セミナー一覧'!$O$2:$O$685,A34,'セミナー一覧'!$D$2:$D$685,"8月") | H34: =COUNTIFS('セミナー一覧'!$O$2:$O$685,A34,'セミナー一覧'!$D$2:$D$685,"9月")
A35: 合計 | B35: =SUM(B32:B34) | C35: =SUM(C32:C34) | D35: =SUM(D32:D34) | E35: =SUM(E32:E34) | F35: =SUM(F32:F34) | G35: =SUM(G32:G34) | H35: =SUM(H32:H34)
A37: AIエージェント/MCP | B37: 件数 | C37: 開催回数計 | D37: 集客数判明 | E37: 参加・申込・来場の合計 | F37: 7月 | G37: 8月 | H37: 9月
A38: AIエージェント | B38: =COUNTIF('セミナー一覧'!$N$2:$N$685,A38) | C38: =SUMIFS('セミナー一覧'!$E$2:$E$685,'セミナー一覧'!$N$2:$N$685,A38) | D38: =COUNTIFS('セミナー一覧'!$N$2:$N$685,A38,'セミナー一覧'!$P$2:$P$685,">0") | E38: =SUMIFS('セミナー一覧'!$P$2:$P$685,'セミナー一覧'!$N$2:$N$685,A38,'セミナー一覧'!$Q$2:$Q$685,"<>定員",'セミナー一覧'!$Q$2:$Q$685,"<>予定来場者数") | F38: =COUNTIFS('セミナー一覧'!$N$2:$N$685,A38,'セミナー一覧'!$D$2:$D$685,"7月") | G38: =COUNTIFS('セミナー一覧'!$N$2:$N$685,A38,'セミナー一覧'!$D$2:$D$685,"8月") | H38: =COUNTIFS('セミナー一覧'!$N$2:$N$685,A38,'セミナー一覧'!$D$2:$D$685,"9月")
A39: AIエージェント（AX） | B39: =COUNTIF('セミナー一覧'!$N$2:$N$685,A39) | C39: =SUMIFS('セミナー一覧'!$E$2:$E$685,'セミナー一覧'!$N$2:$N$685,A39) | D39: =COUNTIFS('セミナー一覧'!$N$2:$N$685,A39,'セミナー一覧'!$P$2:$P$685,">0") | E39: =SUMIFS('セミナー一覧'!$P$2:$P$685,'セミナー一覧'!$N$2:$N$685,A39,'セミナー一覧'!$Q$2:$Q$685,"<>定員",'セミナー一覧'!$Q$2:$Q$685,"<>予定来場者数") | F39: =COUNTIFS('セミナー一覧'!$N$2:$N$685,A39,'セミナー一覧'!$D$2:$D$685,"7月") | G39: =COUNTIFS('セミナー一覧'!$N$2:$N$685,A39,'セミナー一覧'!$D$2:$D$685,"8月") | H39: =COUNTIFS('セミナー一覧'!$N$2:$N$685,A39,'セミナー一覧'!$D$2:$D$685,"9月")
A40: AIエージェント（一部セッション） | B40: =COUNTIF('セミナー一覧'!$N$2:$N$685,A40) | C40: =SUMIFS('セミナー一覧'!$E$2:$E$685,'セミナー一覧'!$N$2:$N$685,A40) | D40: =COUNTIFS('セミナー一覧'!$N$2:$N$685,A40,'セミナー一覧'!$P$2:$P$685,">0") | E40: =SUMIFS('セミナー一覧'!$P$2:$P$685,'セミナー一覧'!$N$2:$N$685,A40,'セミナー一覧'!$Q$2:$Q$685,"<>定員",'セミナー一覧'!$Q$2:$Q$685,"<>予定来場者数") | F40: =COUNTIFS('セミナー一覧'!$N$2:$N$685,A40,'セミナー一覧'!$D$2:$D$685,"7月") | G40: =COUNTIFS('セミナー一覧'!$N$2:$N$685,A40,'セミナー一覧'!$D$2:$D$685,"8月") | H40: =COUNTIFS('セミナー一覧'!$N$2:$N$685,A40,'セミナー一覧'!$D$2:$D$685,"9月")
A41: AIエージェント（扱いは小さい） | B41: =COUNTIF('セミナー一覧'!$N$2:$N$685,A41) | C41: =SUMIFS('セミナー一覧'!$E$2:$E$685,'セミナー一覧'!$N$2:$N$685,A41) | D41: =COUNTIFS('セミナー一覧'!$N$2:$N$685,A41,'セミナー一覧'!$P$2:$P$685,">0") | E41: =SUMIFS('セミナー一覧'!$P$2:$P$685,'セミナー一覧'!$N$2:$N$685,A41,'セミナー一覧'!$Q$2:$Q$685,"<>定員",'セミナー一覧'!$Q$2:$Q$685,"<>予定来場者数") | F41: =COUNTIFS('セミナー一覧'!$N$2:$N$685,A41,'セミナー一覧'!$D$2:$D$685,"7月") | G41: =COUNTIFS('セミナー一覧'!$N$2:$N$685,A41,'セミナー一覧'!$D$2:$D$685,"8月") | H41: =COUNTIFS('セミナー一覧'!$N$2:$N$685,A41,'セミナー一覧'!$D$2:$D$685,"9月")
A42: AIエージェント（生成AI中心） | B42: =COUNTIF('セミナー一覧'!$N$2:$N$685,A42) | C42: =SUMIFS('セミナー一覧'!$E$2:$E$685,'セミナー一覧'!$N$2:$N$685,A42) | D42: =COUNTIFS('セミナー一覧'!$N$2:$N$685,A42,'セミナー一覧'!$P$2:$P$685,">0") | E42: =SUMIFS('セミナー一覧'!$P$2:$P$685,'セミナー一覧'!$N$2:$N$685,A42,'セミナー一覧'!$Q$2:$Q$685,"<>定員",'セミナー一覧'!$Q$2:$Q$685,"<>予定来場者数") | F42: =COUNTIFS('セミナー一覧'!$N$2:$N$685,A42,'セミナー一覧'!$D$2:$D$685,"7月") | G42: =COUNTIFS('セミナー一覧'!$N$2:$N$685,A42,'セミナー一覧'!$D$2:$D$685,"8月") | H42: =COUNTIFS('セミナー一覧'!$N$2:$N$685,A42,'セミナー一覧'!$D$2:$D$685,"9月")
A43: AI営業自動化 | B43: =COUNTIF('セミナー一覧'!$N$2:$N$685,A43) | C43: =SUMIFS('セミナー一覧'!$E$2:$E$685,'セミナー一覧'!$N$2:$N$685,A43) | D43: =COUNTIFS('セミナー一覧'!$N$2:$N$685,A43,'セミナー一覧'!$P$2:$P$685,">0") | E43: =SUMIFS('セミナー一覧'!$P$2:$P$685,'セミナー一覧'!$N$2:$N$685,A43,'セミナー一覧'!$Q$2:$Q$685,"<>定員",'セミナー一覧'!$Q$2:$Q$685,"<>予定来場者数") | F43: =COUNTIFS('セミナー一覧'!$N$2:$N$685,A43,'セミナー一覧'!$D$2:$D$685,"7月") | G43: =COUNTIFS('セミナー一覧'!$N$2:$N$685,A43,'セミナー一覧'!$D$2:$D$685,"8月") | H43: =COUNTIFS('セミナー一覧'!$N$2:$N$685,A43,'セミナー一覧'!$D$2:$D$685,"9月")
A44: MCP | B44: =COUNTIF('セミナー一覧'!$N$2:$N$685,A44) | C44: =SUMIFS('セミナー一覧'!$E$2:$E$685,'セミナー一覧'!$N$2:$N$685,A44) | D44: =COUNTIFS('セミナー一覧'!$N$2:$N$685,A44,'セミナー一覧'!$P$2:$P$685,">0") | E44: =SUMIFS('セミナー一覧'!$P$2:$P$685,'セミナー一覧'!$N$2:$N$685,A44,'セミナー一覧'!$Q$2:$Q$685,"<>定員",'セミナー一覧'!$Q$2:$Q$685,"<>予定来場者数") | F44: =COUNTIFS('セミナー一覧'!$N$2:$N$685,A44,'セミナー一覧'!$D$2:$D$685,"7月") | G44: =COUNTIFS('セミナー一覧'!$N$2:$N$685,A44,'セミナー一覧'!$D$2:$D$685,"8月") | H44: =COUNTIFS('セミナー一覧'!$N$2:$N$685,A44,'セミナー一覧'!$D$2:$D$685,"9月")
A45: 両方 | B45: =COUNTIF('セミナー一覧'!$N$2:$N$685,A45) | C45: =SUMIFS('セミナー一覧'!$E$2:$E$685,'セミナー一覧'!$N$2:$N$685,A45) | D45: =COUNTIFS('セミナー一覧'!$N$2:$N$685,A45,'セミナー一覧'!$P$2:$P$685,">0") | E45: =SUMIFS('セミナー一覧'!$P$2:$P$685,'セミナー一覧'!$N$2:$N$685,A45,'セミナー一覧'!$Q$2:$Q$685,"<>定員",'セミナー一覧'!$Q$2:$Q$685,"<>予定来場者数") | F45: =COUNTIFS('セミナー一覧'!$N$2:$N$685,A45,'セミナー一覧'!$D$2:$D$685,"7月") | G45: =COUNTIFS('セミナー一覧'!$N$2:$N$685,A45,'セミナー一覧'!$D$2:$D$685,"8月") | H45: =COUNTIFS('セミナー一覧'!$N$2:$N$685,A45,'セミナー一覧'!$D$2:$D$685,"9月")
A46: 両方（MCPが中心） | B46: =COUNTIF('セミナー一覧'!$N$2:$N$685,A46) | C46: =SUMIFS('セミナー一覧'!$E$2:$E$685,'セミナー一覧'!$N$2:$N$685,A46) | D46: =COUNTIFS('セミナー一覧'!$N$2:$N$685,A46,'セミナー一覧'!$P$2:$P$685,">0") | E46: =SUMIFS('セミナー一覧'!$P$2:$P$685,'セミナー一覧'!$N$2:$N$685,A46,'セミナー一覧'!$Q$2:$Q$685,"<>定員",'セミナー一覧'!$Q$2:$Q$685,"<>予定来場者数") | F46: =COUNTIFS('セミナー一覧'!$N$2:$N$685,A46,'セミナー一覧'!$D$2:$D$685,"7月") | G46: =COUNTIFS('セミナー一覧'!$N$2:$N$685,A46,'セミナー一覧'!$D$2:$D$685,"8月") | H46: =COUNTIFS('セミナー一覧'!$N$2:$N$685,A46,'セミナー一覧'!$D$2:$D$685,"9月")
A47: 両方（要確認） | B47: =COUNTIF('セミナー一覧'!$N$2:$N$685,A47) | C47: =SUMIFS('セミナー一覧'!$E$2:$E$685,'セミナー一覧'!$N$2:$N$685,A47) | D47: =COUNTIFS('セミナー一覧'!$N$2:$N$685,A47,'セミナー一覧'!$P$2:$P$685,">0") | E47: =SUMIFS('セミナー一覧'!$P$2:$P$685,'セミナー一覧'!$N$2:$N$685,A47,'セミナー一覧'!$Q$2:$Q$685,"<>定員",'セミナー一覧'!$Q$2:$Q$685,"<>予定来場者数") | F47: =COUNTIFS('セミナー一覧'!$N$2:$N$685,A47,'セミナー一覧'!$D$2:$D$685,"7月") | G47: =COUNTIFS('セミナー一覧'!$N$2:$N$685,A47,'セミナー一覧'!$D$2:$D$685,"8月") | H47: =COUNTIFS('セミナー一覧'!$N$2:$N$685,A47,'セミナー一覧'!$D$2:$D$685,"9月")
A48: 合計 | B48: =SUM(B38:B47) | C48: =SUM(C38:C47) | D48: =SUM(D38:D47) | E48: =SUM(E38:E47) | F48: =SUM(F38:F47) | G48: =SUM(G38:G47) | H48: =SUM(H38:H47)
A50: 凡例・注意事項
A51: ・関連度: ◎＝タイトルにAIエージェント/MCP関連語があり、テーマが業務（生産性・営業・製造）に合うもの／○＝どちらか一方だけ合うもの／△＝本文にだけ関連語があり、テーマも技術寄りのもの。
A52: ・抽出方法: 個別確認＝公式サイトやPR TIMESで内容を確認したもの（第1版の55件）／タイトル一致・本文一致＝プラットフォーム巡回で、キーワードが見つかった箇所。
A53: ・集客数: connpass・Doorkeeper・こくちーず・TECH PLAYは、掲載ページの参加者数（申込数）を調査時点の表示値で入れています。0や少人数の表示は、外部フォームで申し込むイベントでよく見られます。企業ウェビナーの多くは非公開です。
A54: ・同じタイトル・同じ主催で複数回開かれたセミナーは1行にまとめ、「開催回数」「開催日一覧」に回数と日付を、集客数に全回の合計を入れています。
A55: ・「参加・申込・来場の合計」は、定員と予定値を除いた実数だけを足した値です。種別の違う数値を合計しているため、目安として見てください。
A56: ・Peatixは、この環境からの直接アクセスがCloudFrontに拒否される（403）ため、検索エンジン経由（site:peatix.com）で集めました。そのため網羅できていない可能性があります。
A57: ・MarkeZine / EnterpriseZine / BOXIL（403）、ITmedia・TechTarget（404）、bizplay（接続不可）、Zoom Events（401）、EventRegist（検索非公開）は、一覧を巡回できませんでした。
A58: ・自動抽出の行（タイトル一致・本文一致）は、テーマ分類をキーワードで機械的に判定しています。誤分類が含まれる可能性があります。
A59: ・AIエージェント/MCPの明記がない生成AIセミナー等は「参考」シートに分けています。

Sheet セミナー企画案
A1: みえるクラウド®ログ｜セミナー企画案20本（市場調査にもとづく）
A2: 青字・黄色セル＝入力欄（仮置きの値。実績に合わせて書き換えてください）。想定参加者と想定デモ予約は数式で自動計算します。
A4: 前提条件
A5: 参加率（申込→当日参加） | B5: 0.5 | C5: 仮置き。無料ウェビナーの一般的な水準として置いた値で、自社実績で上書きしてください
A6: デモ予約率（参加→45分デモ予約） | B6: 0.08 | C6: 仮置き。自社実績で上書きしてください
A8: No | B8: 優先度 | C8: カテゴリ | D8: セミナータイトル案 | E8: ターゲット | F8: 市場の根拠（調査データ） | G8: みえるクラウドの訴求ポイント | H8: 推奨形式 | I8: 尺 | J8: 推奨告知チャネル | K8: 共催・登壇候補 | L8: 目標申込数 | M8: 想定参加者数 | N8: 想定デモ予約数 | O8: CTA（導線） | P8: 開催予定月 | Q8: ステータス | R8: 担当
A9: 1 | B9: S | C9: A. 業務データ×MCP | D9: 「今月のAさんの業務を教えて」とAIに聞くだけ｜PCログ×Claude(MCP)ライブ実演 | E9: 経営者・管理職（従業員50名以上） | F9: MCPセミナーは36件と少なく、大半が開発者向け。kintone・SalesforceのMCP回（136名）やSpeeda MCP（申込終了）の例から、業務データ×MCPの需要は確認できる | G9: 日本初のPCログ×MCP連携。専門知識なしに「聞くだけ」で示唆が得られる | H9: オンライン（ライブデモ） | I9: 45分 | J9: connpass / TECH PLAY / Peatix / 自社メルマガ | K9: Claude関連コミュニティ | L9: 60 | M9: =ROUND(L9*$B$5,0) | N9: =ROUND(M9*$B$6,1) | O9: MCP活用プランのデモ予約 | Q9: 未着手
A10: 2 | B10: A | C10: A. 業務データ×MCP | D10: 非エンジニア管理職のためのMCP入門｜社内データをAIにつなぐと何が変わるか | E10: 管理職・DX担当 | F10: 非エンジニア向けは46件（集客中央値17名）。Claude系は154件と最大テーマ | G10: MCPをPCログで具体的に体感できる | H10: オンライン | I10: 60分 | J10: connpass / TECH PLAY | K10: — | L10: 40 | M10: =ROUND(L10*$B$5,0) | N10: =ROUND(M10*$B$6,1) | O10: 資料請求・デモ予約 | Q10: 未着手
A11: 3 | B11: A | C11: A. 業務データ×MCP | D11: Claude Cowork×PCログで、業務報告・評価資料・工数レポートを自動作成するハンズオン | E11: 管理職・人事 | F11: ハンズオン・実演は84件。日報・業務報告は13件でほぼ空白 | G11: 業務報告や評価資料をAIが自動作成する（MCP活用プランの機能） | H11: 会場（銀座）＋オンライン | I11: 90分 | J11: Peatix / connpass | K11: — | L11: 25 | M11: =ROUND(L11*$B$5,0) | N11: =ROUND(M11*$B$6,1) | O11: トライアル・デモ予約 | Q11: 未着手
A12: 4 | B12: B | C12: A. 業務データ×MCP | D12: MCP連携で社内ツールを横断分析｜PCログ×カレンダー×チャットの合同ウェビナー | E12: 情シス・DX推進 | F12: データ連携・データ基盤は18件（平均52名）。SaaS横断のMCP回は集客が良い | G12: カレンダーやチャットと組み合わせた高精度な業務分析 | H12: オンライン（共催） | I12: 60分 | J12: 共催先の会員網 / マジセミ | K12: 連携先SaaS（カレンダー・チャット等） | L12: 80 | M12: =ROUND(L12*$B$5,0) | N12: =ROUND(M12*$B$6,1) | O12: デモ予約 | Q12: 未着手
A13: 5 | B13: S | C13: B. AIの定着・ガバナンス | D13: 「AIを入れたのに使われない」を数字で見る｜社内のAI利用実態を可視化する方法 | E13: 経営者・DX推進 | F13: 定着・PoC止まりは28件で、課題として顕在化している。競合は「定着支援」の話が中心で、実態を計測する切り口は少ない | G13: 「社内で誰がAIをよく使っているか」にAIが答える | H13: オンライン | I13: 45分 | J13: マジセミ / Doorkeeper / 自社メルマガ | K13: 生成AI研修会社 | L13: 50 | M13: =ROUND(L13*$B$5,0) | N13: =ROUND(M13*$B$6,1) | O13: デモ予約 | Q13: 未着手
A14: 6 | B14: A | C14: B. AIの定着・ガバナンス | D14: シャドーAI対策の第一歩｜誰がどのAIツールを使っているかを把握する | E14: 情シス・経営企画 | F14: ガバナンス・セキュリティは40件（平均35名）と集客が安定している | G14: PCログでAIツールの利用状況を記録・把握できる | H14: オンライン | I14: 45分 | J14: マジセミ / ビジネス+IT | K14: セキュリティベンダー | L14: 50 | M14: =ROUND(L14*$B$5,0) | N14: =ROUND(M14*$B$6,1) | O14: 資料請求 | Q14: 未着手
A15: 7 | B15: B | C15: B. AIの定着・ガバナンス | D15: AIエージェント時代の情報漏洩対策｜操作ログ・USB・印刷履歴で守る | E15: 情シス・総務 | F15: AIエージェントのセキュリティは、企業ウェビナーの定番テーマ | G15: 「いつ・どこで・誰が」を記録。USBや印刷の履歴も残る | H15: オンライン | I15: 45分 | J15: マジセミ / Doorkeeper | K15: — | L15: 40 | M15: =ROUND(L15*$B$5,0) | N15: =ROUND(M15*$B$6,1) | O15: 資料請求 | Q15: 未着手
A16: 8 | B16: A | C16: B. AIの定着・ガバナンス | D16: 生成AI投資のROIを測る｜導入前後の工数をPCログで比較する | E16: 経営者・経営企画 | F16: 工数・可視化は14件で空白。PoC止まりの層は効果測定の方法を求めている | G16: プロジェクトごとの工数とボトルネックをAIが分析する | H16: オンライン | I16: 45分 | J16: ビジネス+IT / 自社メルマガ | K16: — | L16: 40 | M16: =ROUND(L16*$B$5,0) | N16: =ROUND(M16*$B$6,1) | O16: デモ予約 | Q16: 未着手
A17: 9 | B17: A | C17: C. 人事評価・健康経営 | D17: MVVに照らしてAIが評価の下書きを作る｜データに基づく人事評価の実演 | E17: 人事・経営者 | F17: 評価・人事は33件。MVVとデータを組み合わせたAI評価の切り口は見当たらない | G17: 「MVVに照らしたB氏の業務評価」を実演する | H17: オンライン（ライブデモ） | I17: 45分 | J17: Peatix / HR系メディア | K17: 人事コンサル・HR団体 | L17: 50 | M17: =ROUND(L17*$B$5,0) | N17: =ROUND(M17*$B$6,1) | O17: デモ予約 | Q17: 未着手
A18: 10 | B18: B | C18: C. 人事評価・健康経営 | D18: 「隠れた貢献」を見落とさない｜リモート時代の公正な評価とフィードバック | E18: 管理職・人事 | F18: リモートでの評価を扱うAIセミナーは今回の調査で0件 | G18: 頑張りを定量データで可視化する | H18: オンライン | I18: 45分 | J18: Peatix / 自社メルマガ | K18: — | L18: 30 | M18: =ROUND(L18*$B$5,0) | N18: =ROUND(M18*$B$6,1) | O18: 資料請求 | Q18: 未着手
A19: 11 | B19: S | C19: C. 人事評価・健康経営 | D19: 健康経営×AI｜深夜・休日の稼働傾向からフォローすべきメンバーを見つける | E19: 人事・総務・健康経営担当 | F19: 健康経営・労務は14件でほぼ空白。AIを絡めたものはさらに少ない | G19: AIが深夜稼働の傾向を検知し、フォローすべき人を教えてくれる | H19: オンライン | I19: 45分 | J19: 健康経営関連団体 / Peatix | K19: 健康経営支援企業・産業医サービス | L19: 50 | M19: =ROUND(L19*$B$5,0) | N19: =ROUND(M19*$B$6,1) | O19: デモ予約 | Q19: 未着手
A20: 12 | B20: B | C20: C. 人事評価・健康経営 | D20: 社労士と考える労務リスク｜客観的な労働時間の記録とAI分析 | E20: 中小企業の経営者・総務 | F20: 労務×AIの供給は少ない。士業との共催は信頼を得やすい | G20: 客観的な稼働記録を残し、長時間労働を未然に防ぐ | H20: オンライン | I20: 60分 | J20: グループ顧客網 / こくちーず | K20: セブンセンス社会保険労務士法人 | L20: 40 | M20: =ROUND(L20*$B$5,0) | N20: =ROUND(M20*$B$6,1) | O20: 資料請求 | Q20: 未着手
... A28: 20 | B28: A | C28: F. 形式・地域 | D28: 月例30分「AIに聞いてみた」ライブ｜視聴者の質問をその場でPCログAIに投げる | E28: 見込み顧客全般 | F28: connpassでは、回数を重ねるAIエージェント勉強会（#90回で毎回50〜60名程度）のような定例シリーズの型が定着している | G28: 「聞くだけ」を毎月体験してもらう | H28: オンライン（定例） | I28: 30分 | J28: connpass（グループ化） / 自社メルマガ | K28: — | L28: 30 | M28: =ROUND(L28*$B$5,0) | N28: =ROUND(M28*$B$6,1) | O28: デモ予約（毎月） | Q28: 未着手
D29: 合計 | L29: =SUM(L9:L28) | M29: =SUM(M9:M28) | N29: =SUM(N9:N28)
C31: 優先度別
C32: 優先度 | D32: 本数 | E32: 目標申込 | F32: 想定デモ予約
C33: S | D33: =COUNTIF($B$9:$B$28,C33) | E33: =SUMIF($B$9:$B$28,C33,$L$9:$L$28) | F33: =SUMIF($B$9:$B$28,C33,$N$9:$N$28)
C34: A | D34: =COUNTIF($B$9:$B$28,C34) | E34: =SUMIF($B$9:$B$28,C34,$L$9:$L$28) | F34: =SUMIF($B$9:$B$28,C34,$N$9:$N$28)
C35: B | D35: =COUNTIF($B$9:$B$28,C35) | E35: =SUMIF($B$9:$B$28,C35,$L$9:$L$28) | F35: =SUMIF($B$9:$B$28,C35,$N$9:$N$28)
C37: 優先度: S＝空白が大きく、自社の強みが直接効き、MCP活用プランへの導線が短いもの（最初の四半期に実施）／A＝次に実施／B＝共催先や事例が確保できしだい実施。
C38: 目標申込数は仮置きです。今回の調査では、プラットフォーム上の集客中央値が10〜20名、100名を超えるのは共催や定例シリーズが中心でした。
C39: 開催予定月・ステータス・担当は空欄です。記入してお使いください（ステータスはプルダウンで選択）。

Sheet 市場ニーズ分析
A1: 市場ニーズ分析：キーワード別の開催件数と集客（2026/7〜9月・684件）
A2: 出典: 「セミナー一覧」シートの全684件。セミナー名と概要を正規表現で分類して集計した値（Pythonで算出）です。集客の平均・中央値には、参加者数・申込者数が公開されているイベントだけを使っています。定員と非公開のものは除外しています。
A4: キーワード群 | B4: 判定に使った語 | C4: 開催件数 | D4: 集客判明件数 | E4: 平均集客（名） | F4: 集客中央値（名） | G4: 示唆
A5: Claude（Code / Cowork） | B5: Claude Code|Claude Cowork | C5: 154 | D5: 115 | E5: 88 | F5: 18 | G5: 供給が最も多いテーマ。ツールの使い方講座に偏っている
A6: MCP | B6: MCP | C6: 36 | D6: 18 | E6: 33 | F6: 12 | G6: 大半が開発者向け。業務データ×MCPを経営層・管理職向けに扱うものはほぼ空白
A7: Copilot | B7: Copilot | C7: 25 | D7: 13 | E7: 356 | F7: 7 | G7: 大規模な勉強会が平均値を押し上げている
A8: 経営者向け | B8: 経営者|経営層|社長|決裁者 | C8: 57 | D8: 26 | E8: 13 | F8: 6 | G8: 件数は多いが、1回あたりの集客は小さい
A9: 士業・税理士・会計 | B9: 士業|税理士|会計事務所 | C9: 8 | D9: 2 | E9: 1 | F9: 1 | G9: 件数は少ない。ただしfreee Advisor Dayの前年参加者は約2,000名で、需要は大きい
A10: AIの定着・PoC止まり | B10: 定着|PoC|使われない|成果が出ない | C10: 28 | D10: 12 | E10: 6 | F10: 6 | G10: 「導入したが使われない」課題が顕在化している
A11: ガバナンス・セキュリティ・権限 | B11: ガバナンス|セキュリティ|権限|シャドー | C11: 40 | D11: 16 | E11: 35 | F11: 18 | G11: 集客が比較的安定している
A12: 暗黙知・属人化・ナレッジ | B12: 暗黙知|属人|ナレッジ|伝承 | C12: 34 | D12: 11 | E12: 2 | F12: 1 | G12: 関心は高く、企業ウェビナーが中心
A13: 工数・可視化 | B13: 工数|可視化|見える化 | C13: 14 | D13: 3 | E13: 4 | F13: 1 | G13: ほぼ空白。みえるクラウドの強みの領域
A14: 評価・人事・HR | B14: 評価|人事|HR|採用|人材 | C14: 33 | D14: 15 | E14: 57 | F14: 7 | G14: MVVに基づく評価は差別化の余地がある
A15: 健康経営・労務・働き方 | B15: 健康経営|労務|長時間|働き方|残業 | C15: 14 | D15: 3 | E15: 12 | F15: 3 | G15: ほぼ空白。AIと組み合わせたものはさらに少ない
A16: 非エンジニア向け | B16: 非エンジニア|コードを書かない|ノーコード|初心者 | C16: 46 | D16: 29 | E16: 29 | F16: 17 | G16: 非エンジニア向けの需要は大きい
... A21: 製造業 | B21: 製造|工場|ものづくり | C21: 33 | D21: 6 | E21: 37 | F21: 30 | G21: 集客が判明しているものは30名前後で安定している
A23: 空白度 | B23: ="開催件数20件未満のキーワード群："&COUNTIF(C5:C21,"<20")&"群"

Sheet セミナー一覧
A1: No | B1: 開催日（初回） | C1: 開催日（最終） | D1: 開催月 | E1: 開催回数 | F1: 開催日一覧（複数回） | G1: セミナー名 | H1: 主催者 | I1: 共催・登壇 | J1: 掲載プラットフォーム | K1: 形式 | L1: 会場・場所 | M1: テーマ分類 | N1: AIエージェント/MCP | O1: 関連度 | P1: 集客数 | Q1: 集客数の種別 | R1: 定員 | S1: 集客数の補足 | T1: 概要・抜粋 | U1: ソースURL | V1: 補足URL | W1: 抽出方法 | X1: 備考
A2: 1 | B2: 46204 | C2: 46204 | D2: =MONTH(B2)&"月" | E2: 1 | G2: AIコーディング時代の設計判断力を鍛える ―失敗パターンから学ぶ“動く”の先の考え方 | H2: Findy/ファインディ | J2: TECH PLAY | K2: オンライン | M2: 開発生産性 | N2: AIエージェント | O2: △ | P2: 149 | Q2: 申込者数 | R2: 200 | T2: ✍️概要 AIコーディングエージェントが急速に普及する中、「動く」ものが簡単に生成されるようになりました。しかし、価値あるシステムを構築するためには、人間の設計判断力がこれまで以上に重要となります。 本イベントでは、kawasimaさんが整理された『Decision Quality と設計判断失敗パターン』を基に、設計判断の失敗パターンを解説いただきます。 また、kawasimaさんが作成中の、コーディングエージェントを活用した失敗パタ | U2: https://techplay.jp/event/996755 | W2: 本文一致
A3: 2 | B3: 46204 | C3: 46204 | D3: =MONTH(B3)&"月" | E3: 1 | G3: Codexで管理職の仕事をラクにする 第3回：部下ごとの報告・面談資料編 | H3: はんなりプログラミングの会 | J3: connpass | K3: オンライン | L3: youtube live | M3: 開発生産性 | N3: AIエージェント | O3: ○ | P3: 1 | Q3: 参加者数 | R3: 20 | U3: https://hannari-python.connpass.com/event/397219/ | W3: タイトル一致
A4: 3 | B4: 46204 | C4: 46204 | D4: =MONTH(B4)&"月" | E4: 1 | G4: 【CeeBeeDee】Claude Code スキルでここまでできる！〜オリジナルスキルのススメ／こもりまさあき | H4: CeeBeeDee | J4: Doorkeeper | K4: 不明 | M4: 開発生産性 | N4: AIエージェント | O4: ○ | P4: 92 | Q4: 参加者数 | T4: Web制作の現場ですぐに使えるClaude Codeの「スキル」について、実例とデモを交えて、こもりまさあきさんに解説いただきます。 本イベントは有料イベントとして開催します。 無料での配信は行わず、お申し込みいただいた方のみに配信URLをお知らせします。 アーカイブ（と当日の配信）はサブスクの対象ですが、こもりまさあきさんの 「KMRVID Claude Skills」講座 （15,400円）は付属しません。 手作業から解放される！ | U4: https://cssnite.doorkeeper.jp/events/197993 | W4: タイトル一致
A5: 4 | B5: 46204 | C5: 46206 | D5: =MONTH(B5)&"月" | E5: 1 | G5: ものづくり ワールド［東京］2026 | H5: RX Japan | J5: 個別調査（公式サイト・PR TIMES等） | K5: 会場 | L5: 東京ビッグサイト | M5: 生産管理・製造・SCM | N5: AIエージェント | O5: ◎ | P5: 81697 | Q5: 来場者数 | S5: 3日間の合計（併催展を含む）。7/1は20,534名、7/2は25,577名、7/3は35,586名。 | T5: 日本最大級の製造業展示会。製造業DX展、製造業×フィジカルAI展、設計・製造ソリューション展などで構成されている。 | U5: https://www.manufacturing-world.jp/tokyo/ja-jp/previous/visitorcount.html | W5: 個別確認 | X5: 展示会。AIエージェント専門の展示ではない
A6: 5 | B6: 46205 | C6: 46205 | D6: =MONTH(B6)&"月" | E6: 1 | G6: AgentCoreハーネスとマネージドKBでRAG & AIエージェント構築を体験！ | H6: JAWS-UG東京 | J6: connpass | K6: オンライン | L6: Zoom | M6: 技術・AI全般 | N6: AIエージェント | O6: ○ | P6: 316 | Q6: 参加者数 | U6: https://jawsug.connpass.com/event/398118/ | W6: タイトル一致
A7: 6 | B7: 46205 | C7: 46205 | D7: =MONTH(B7)&"月" | E7: 1 | G7: EMLinkウェビナー開催：「AIエージェントに選ばれる」設備保全データ整備 — AI活用の成否は、データの整え方で決まる（7月2日・参加無料） | H7: EMLink（株式会社設備保全総合研究所） | J7: PR TIMES | K7: online | L7: オンライン（Teamsウェビナー：事前登録制）／参加無料 | M7: 生産管理・製造・SCM | N7: AIエージェント | O7: ◎ | Q7: 不明 | T7: 工場・インフラ向け設備保全クラウド『EMLink』を提供する株式会社設備保全総合研究所は、ウェビナー「AIエージェントに選ばれる設備保全データ整備」を2026年7月2日（木）14:00より開催します。検索の世界で「AIに選ばれる情報設計」が注目されているように、設備保全の世界でも、AIエージェントが参照できる形にデータを整えることが、AI活用の成果を左右します。 これから生成AI・AIエージェントを保全・設備管理業務に取り入れたい方、「 | U7: https://prtimes.jp/main/html/rd/p/000000032.000115057.html | W7: タイトル一致
A8: 7 | B8: 46205 | C8: 46205 | D8: =MONTH(B8)&"月" | E8: 1 | G8: Hardening Designers Conference 2026 | H8: hardening | J8: Doorkeeper | K8: 不明 | M8: 営業・マーケ・CS | N8: AIエージェント | O8: ○ | P8: 210 | Q8: 参加者数 | R8: 265 | T8: 📅 開催日時 DAY1 7/2(木) 10:00–17:00 ── Training Session / Micro Hardening（ マルチトラック並行開催 ） DAY2 7/3(金) 13:00–18:00 ── Conference Day｜Tech Showcase & Open Mic DAY3 7/4(土) 09:00–18:00 ── Conference Day｜Deep Session 🎯 このカンファレンスで得 | U8: https://hardening.doorkeeper.jp/events/196978 | W8: 本文一致
A9: 8 | B9: 46205 | C9: 46205 | D9: =MONTH(B9)&"月" | E9: 1 | G9: 【無料オンライン】Claude Code勉強会 -入門編- | H9: 株式会社ビズリンク 事務所 | J9: こくちーずプロ | K9: オンライン | L9: オンライン 日本 | M9: 開発生産性 | N9: AIエージェント | O9: ○ | Q9: 不明 | T9: 【無料】「相談する」AIから「任せる」AIへ。 ─Claude Code勉強会＜入門編＞ー 導入編と実践編、参加者100名突破しました！ 経営者限定の導入編はこちら！ 【完全無料・オンライン・60分】 「ChatGPTは使っているが、仕事の速さも量も変わっていない」 「AIを活用している人との差が、なんとなく広がっている気がする」 ──そんな方のための、自律型AI「Claude Code」入門ウェビナーです。 AIに"相談する"時代から | U9: https://www.kokuchpro.com/event/a91b6275bcbfff0a1e04532f6c25ecf3/3817804/ | W9: タイトル一致
A10: 9 | B10: 46206 | C10: 46206 | D10: =MONTH(B10)&"月" | E10: 1 | G10: AI駆動開発の最前線 ～シアトル発・Biz × Techを繋ぐAI Native開発プロセス～【Slalom Tech Night vol.1】 | H10: Slalom株式会社 | J10: TECH PLAY | K10: ハイブリッド | L10: 現地参加の場合：愛宕グリーンヒルズMORIタワー7F／オンラインの場合：Zoomウェビナー 〒105-6207 東京都港区愛宕2-5-1 愛宕グリーンヒルズMORIタワー7F | M10: 営業・マーケ・CS | N10: AIエージェント | O10: ○ | P10: 375 | Q10: 申込者数 | R10: 370 | T10: 概要 生成AIの進化によって、ソフトウェア開発は大きく変わり始めています。 コード生成やAIエージェントによって実装スピードは加速する一方で、実際の開発現場では、 ・要件定義と実装が分断される ・AI活用が部分最適に留まる ・設計や意思決定がボトルネックになる ・「何を作るべきか」を定義できる人材が不足する といった新たな課題も見え始めています。 では、AI Native時代のプロダクト開発は、どのように変わるのでしょうか。 本イベント | U10: https://techplay.jp/event/995896 | W10: 本文一致
A11: 10 | B11: 46206 | C11: 46206 | D11: =MONTH(B11)&"月" | E11: 1 | G11: Cursor meetup Nagoya #1 | H11: AIエージェントユーザー会（AIAU） | J11: connpass | K11: 会場 | L11: 〒460-0008 愛知県名古屋市中区栄４丁目１−１ | M11: 開発生産性 | N11: AIエージェント | O11: ○ | P11: 3 | Q11: 参加者数 | R11: 55 | U11: https://aiau.connpass.com/event/396073/ | W11: タイトル一致
A12: 11 | B12: 46206 | C12: 46206 | D12: =MONTH(B12)&"月" | E12: 1 | G12: QA・スクラムのための価値駆動開発 —顧客にとって役立つ問いの立て方 | H12: Findy/ファインディ | J12: TECH PLAY | K12: オンライン | M12: 営業・マーケ・CS | N12: AIエージェント | O12: ○ | P12: 14 | Q12: 申込者数 | R12: 100 | T12: ✍️概要 Agentic Codingが日常化したいま、仕様駆動開発は重要な開発プロセスとして広まってきました。 しかし、仕様の手前にある「本当に顧客に価値を届けられるか」を最上流で見極める力が、チームの成果と持続可能性を左右します。 今回ご登壇いただくkubopさんは、価値駆動開発 > 仕様駆動開発 > 振る舞い駆動開発 > テスト駆動開発といった包含関係として捉え、これらを相反するものではなく組み合わせながら活用する実践を提唱してい | U12: https://techplay.jp/event/996433 | W12: 本文一致
A13: 12 | B13: 46206 | C13: 46206 | D13: =MONTH(B13)&"月" | E13: 1 | G13: W&B公式ハンズオン「AI Engineering Dojo」―AIエージェントの評価・改善に挑戦！ | H13: ジェネラティブエージェンツ / Generative Agents | J13: connpass | K13: オンライン | L13: オンライン | M13: 技術・AI全般 | N13: AIエージェント | O13: ○ | P13: 79 | Q13: 参加者数 | R13: 200 | U13: https://generative-agents.connpass.com/event/397776/ | W13: タイトル一致
A14: 13 | B14: 46206 | C14: 46206 | D14: =MONTH(B14)&"月" | E14: 1 | G14: 【CeeBeeDee】Claude Code使いこなせてる？ 挫折しないための使いこなし術／たにぐち まこと | H14: CeeBeeDee | J14: Doorkeeper | K14: 不明 | M14: 開発生産性 | N14: AIエージェント | O14: ○ | P14: 608 | Q14: 参加者数 | T14: 本イベントは終了しています。「アーカイブ動画を見たい方」「スライドをダウンロードしたい方」はSTORESからお求めください。 個人向け（3,300円） ※領収書なし 個人・フリーランス（5,500円） 法人向け（11,000円） 本日現在（7月3日[金]）、194本のアーカイブが見放題になる定額制（サブスク）も用意しています。 3ヶ月ごと：35ドル 12ヶ月ごと：130ドル 動画だけでなく、スライドや補足なども含まれます。 生成AIコ | U14: https://cssnite.doorkeeper.jp/events/197947 | W14: タイトル一致
A15: 14 | B15: 46206 | C15: 46206 | D15: =MONTH(B15)&"月" | E15: 1 | G15: デジタル活用実践セミナー第3弾“超実践型”職場で活かせる「生成AIセミナー」応用編 | H15: 魚津観光まちづくり株式会社 | J15: こくちーずプロ | K15: オフライン（会場） | L15: 魚津商工会議所5階研修室 富山県魚津市釈迦堂1丁目12-18 | M15: 生産性向上・業務効率化 | N15: AIエージェント | O15: ○ | P15: 0 | Q15: 参加者数 | R15: 40 | T15: 【プログラム】 ・AIO（AI最適化）対策への心構えと備え ・AIエージェントの業務活用と社内データ整備 ・事業者向けワンランク上のセキュリティ対策 ＋α：今後のAIトレンドについて 申し込みは以下から https://x.gd/mnuIs https://uozu-machi.com/news/4166/ 【無料個別相談会実施】 公益財団法人富山県新世紀産業機構のご協力により、富山県よろず支援拠点による無料個別相談会も実施します。講演 | U15: https://www.kokuchpro.com/event/a5d256165da52d3d1c762f606d771a51/ | W15: 本文一致
A16: 15 | B16: 46207 | C16: 46285 | D16: =MONTH(B16)&"月" | E16: 5 | F16: 07/04、08/01、08/15、09/05、09/20 | G16: Women Who Go Tokyo読書会 Goで作るセキュリティ分析LLMエージェント #11 | H16: Women Who Go Tokyo | J16: connpass | K16: オンライン | L16: オンライン | M16: 技術・AI全般 | N16: AIエージェント | O16: ○ | P16: 24 | Q16: 参加者数 | R16: 50 | S16: 全5回の合計 | U16: https://womenwhogo-tokyo.connpass.com/event/398081/ | W16: タイトル一致
A17: 16 | B17: 46207 | C17: 46242 | D17: =MONTH(B17)&"月" | E17: 5 | F17: 07/04、07/18、07/25、08/01、08/08 | G17: 【初心者歓迎・無料】ゼロから始めるClaude Code講座 | H17: みんなのグラさんと愉快な仲間たち | J17: connpass | K17: 会場 | L17: 千代田区平河町2-7-2 VORT永田町6F | M17: 開発生産性 | N17: AIエージェント | O17: ○ | P17: 8 | Q17: 参加者数 | S17: 全5回の合計 | U17: https://glass-sun.connpass.com/event/397320/ | W17: タイトル一致
A18: 17 | B18: 46207 | C18: 46207 | D18: =MONTH(B18)&"月" | E18: 1 | G18: 【参加無料】Riding プログラミング講習会のお知らせ【7月4日(土)開催】 | H18: 株式会社Riding | J18: こくちーずプロ | K18: オフライン（会場） | L18: 株式会社Riding 東京都東京都品川区西五反田8-2-8 五反田佑気ビル 9F | M18: 開発生産性 | N18: AIエージェント | O18: △ | P18: 0 | Q18: 参加者数 | R18: 10 | T18: ---- 【参加無料】Riding プログラミング講習会のお知らせ【7月4日(土)開催】 こんにちは！ 第6回Riding主催のプログラミング講習会を下記のとおり開催することとなりました。 第6回目のテーマは ①「Riding研修の卒業制作発表」 ②「ゲスト LiNKCREW 山口さんによる講義」 ③「Claude Codeで始めるループエンジニアリング」 の3本立てです！ 初心者の方ももちろん大歓迎です！ プログラミングを学びながら、 | U18: https://www.kokuchpro.com/event/bb34ad45cb8a954b11e51e243e031fe6/ | W18: 本文一致
A19: 18 | B19: 46207 | C19: 46207 | D19: =MONTH(B19)&"月" | E19: 1 | G19: ゼロからはじめるClaude Code入門講座(対面・無料) | H19: テックジム事務局 | J19: こくちーずプロ | K19: オフライン（会場） | L19: テックジム東京本校 東京都千代田区平河町2-7-2 VORT永田町6F | M19: 開発生産性 | N19: AIエージェント | O19: ○ | P19: 1 | Q19: 参加者数 | R19: 3 | T19: ゼロからはじめるClaude Code講座（対面・無料） 【会場での開催となります】 オンラインでは出来ない細やかなサポートが、リアル開催ならでは！ 初学者から年齢、性別に限らず興味がある方に受講頂いている当講座。 どなたでもお気軽にご参加ください。講座後はテックジム会員様と混ざって頂き自習室を自由にご利用ください。 入退室は自由となっております。※ノートPC持参でお願いします。 あなたの作りたいものを作る 本講座では 「その日のうちに | U19: https://www.kokuchpro.com/event/8d639521d6dab7ff6a25a9a1fff3340e/3819131/ | W19: タイトル一致
A20: 19 | B20: 46207 | C20: 46291 | D20: =MONTH(B20)&"月" | E20: 13 | F20: 07/04、07/11、07/18、07/25、08/01、08/08、08/15、08/22、08/29、09/05、09/12、09/19、09/26 | G20: バイブコーディングクラブ | H20: I Love AI | J20: TECH PLAY | K20: ハイブリッド | L20: エンジニアカフェ 福岡市中央区天神1丁目15番30号 | M20: 開発生産性 | N20: AIエージェント | O20: △ | P20: 13 | Q20: 申込者数 | R20: 52 | S20: 全13回の合計 | T20: バイブコーディングクラブ Claude Code Proプラン支給！挑戦者募集☆（未経験可） 概要 バイブコーディングとは、AIにコーディングを任せて高速に実装する手法です🤖 本イベントでは、挑戦者が持参するアイデアでバイブコーディングを行い、1ヶ月間でプロダクトを完成させます🧠 バイブコーディングクラブウェブサイトで歴代挑戦者の作品を閲覧できます👀 挑戦者 募集中です🔥 非エンジニアでも上級者でも挑戦可能です🙆 参加登録後に支給する1 | U20: https://techplay.jp/event/997598 | W20: 本文一致
A21: 20 | B21: 46208 | C21: 46208 | D21: =MONTH(B21)&"月" | E21: 1 | G21: Microsoft Agent 365 の成長を見守る会 | H21: Microsoft Agent 365 Japan | J21: connpass | K21: オンライン | L21: オンライン | M21: 技術・AI全般 | N21: AIエージェント | O21: ○ | P21: 53 | Q21: 参加者数 | U21: https://agent365jp.connpass.com/event/396638/ | W21: タイトル一致
A22: 21 | B22: 46208 | C22: 46257 | D22: =MONTH(B22)&"月" | E22: 4 | F22: 07/05、07/19、08/02、08/23 | G22: [秋葉原] AI駆動開発 / LLM もくもく会 (初参加・初心者大歓迎！) | H22: コワーキングスペース秋葉原 Weeyble | J22: TECH PLAY | K22: 会場 | L22: コワーキングスペース秋葉原 Weeyble 東京都千代田区神田佐久間町3-37-1 山茂登ビル3F | M22: 開発生産性 | N22: MCP | O22: △ | Q22: 非公開 | R22: 32 | S22: 全4回の合計 | T22: この会について AI駆動開発や大規模言語モデル（LLM）についての理解を深めるためのもくもく会です。 LLMそのものについて勉強したい方はもちろん、LLMを活用しながら他のプログラミングや研究、業務の課題に取り組む方も大歓迎です。 キーワード: Claude Code / Codex / Cline / Cursor / Copilot / MCP / ChatGPT / Gemini / Llama / RAG / LangChain | U22: https://techplay.jp/event/997834 | W22: 本文一致
A23: 22 | B23: 46208 | C23: 46250 | D23: =MONTH(B23)&"月" | E23: 4 | F23: 07/05、07/19、08/02、08/16 | G23: [秋葉原] Amazon Bedrock AgentCore 実践入門 輪読&勉強会 4章ハンズオン | H23: Weeyble データサイエンス | J23: connpass | K23: 会場 | L23: 東京都千代田区神田佐久間町3丁目37-1 山茂登ビル3F Weeyble | M23: 技術・AI全般 | N23: AIエージェント | O23: ○ | P23: 32 | Q23: 参加者数 | R23: 38 | S23: 全4回の合計 | U23: https://weeyble-data.connpass.com/event/398804/ | W23: タイトル一致
A24: 23 | B24: 46208 | C24: 46292 | D24: =MONTH(B24)&"月" | E24: 8 | F24: 07/05、07/12、07/26、08/02、08/23、09/06、09/13、09/27 | G24: 「実践Claude Code入門」読書会 #4 | H24: IT系勉強会 | J24: connpass | K24: オンライン | L24: オンライン | M24: 開発生産性 | N24: AIエージェント | O24: ○ | P24: 32 | Q24: 参加者数 | S24: 全8回の合計 | U24: https://study-group.connpass.com/event/398087/ | W24: タイトル一致
A25: 24 | B25: 46208 | C25: 46208 | D25: =MONTH(B25)&"月" | E25: 1 | G25: 【増枠】小杉湯の隣 Hermes Agent を触る会 | H25: DevAI | J25: connpass | K25: 会場 | L25: 杉並区高円寺北３丁目３２−１７ | M25: 生産管理・製造・SCM | N25: AIエージェント | O25: ◎ | P25: 5 | Q25: 参加者数 | R25: 8 | U25: https://ai-developer-monetization-lab.connpass.com/event/397293/ | W25: タイトル一致
A26: 25 | B26: 46208 | C26: 46208 | D26: =MONTH(B26)&"月" | E26: 1 | G26: 安全に使うClaude Code | H26: デジタルレイバーズ | J26: connpass | K26: オンライン | L26: オンライン | M26: 開発生産性 | N26: AIエージェント | O26: ○ | P26: 22 | Q26: 参加者数 | R26: 30 | U26: https://digital-labors.connpass.com/event/397379/ | W26: タイトル一致
A27: 26 | B27: 46208 | C27: 46208 | D27: =MONTH(B27)&"月" | E27: 1 | G27: 安全に使うClaude Code 〜非エンジニアのための"守りながら使う"実践ガイド〜 | H27: デジタルレイバーズ | J27: TECH PLAY | K27: オンライン | M27: 生産性向上・業務効率化 | N27: AIエージェント | O27: ◎ | P27: 24 | Q27: 申込者数 | R27: 30 | T27: 簡単な紹介 非エンジニアの方が、Claude Codeを安全に使いこなし、データ分析から提案資料の作成、ファイル処理までを実務に落とし込むための実践ガイドです。 イベントについて 本セミナーは、エンジニアではない経営者・幹部・実務担当者の方を対象に、Claude Codeを「プログラム開発のためのツール」ではなく「あらゆる業務を任せられる汎用的なアシスタント」として捉え直すための講義＋デモのセミナーです。 多くの現場では、複雑なデータの | U27: https://techplay.jp/event/997138 | W27: タイトル一致
A28: 27 | B28: 46208 | C28: 46243 | D28: =MONTH(B28)&"月" | E28: 3 | F28: 07/05、07/31、08/09 | G28: 第9回Roblox×AIで、自分だけの ゲームを作ろう！ | H28: gameschool | J28: Doorkeeper | K28: 会場 | L28: 路地裏GarageMarket 〒338-0013 埼玉県さいたま市中央区鈴谷７丁目７−３ | M28: 生産管理・製造・SCM | N28: AIエージェント | O28: ○ | P28: 6 | Q28: 参加者数 | R28: 27 | S28: 全3回の合計 | T28: Robloxでのゲーム作り 🎮 あなたの想像力が、新しいゲームの世界を創る 「遊ぶだけ」から「作る喜び」へ。 Robloxは世界中で2億人以上のユーザーが楽しむゲームの広場。 好きなゲームで遊ぶのも楽しいけれど、「自分だけのゲームを作る」体験はもっと楽しい！ この特別体験イベントでは、プロのゲームクリエイターがあなたのクリエイティブな一歩を全力でサポートします。 これからの時代は、ただ遊ぶだけでなく「自分で作って届ける力」が大きな武器 | U28: https://gameschool.doorkeeper.jp/events/197905 | W28: 本文一致
A29: 28 | B29: 46209 | C29: 46209 | D29: =MONTH(B29)&"月" | E29: 1 | G29: AIエージェントの最新動向とこれからのキャリア【Developers Online】 | H29: Developers Summit | J29: connpass | K29: オンライン | L29: オンライン | M29: 技術・AI全般 | N29: AIエージェント | O29: ○ | P29: 140 | Q29: 参加者数 | R29: 150 | U29: https://devsumi.connpass.com/event/396236/ | W29: タイトル一致
A30: 29 | B30: 46209 | C30: 46209 | D30: =MONTH(B30)&"月" | E30: 1 | G30: AI社員を作るClaude Code入門ウェビナー|経営者向け無料セミナー | H30: AI社員を作るClaude Code入門ウェビナー|経営者向け無料セミナー事務局 | J30: こくちーずプロ | K30: オンライン | L30: オンライン 日本 | M30: 生産性向上・業務効率化 | N30: AIエージェント | O30: ◎ | P30: 0 | Q30: 参加者数 | R30: 30 | T30: 「Claude Code、最近よく聞くけど…正直、何ができるのかよくわからない」 そんな方のための1時間です。コードは書きません。プログラミングの知識も不要。日本語で頼むだけで何ができるのか——実演でそのまま全部お見せします。 Claude Codeを使えば、コードが書けなくても ・営業／マーケ／経理に「AI社員」を配置して、チームで仕事を回せる ・ホームページやLPを、外注せずに自分で作れる ・業務アプリを、その場で作って使い始められ | U30: https://www.kokuchpro.com/event/50d9c59588f29fcd31a0c4bba740d584/ | W30: タイトル一致
A31: 30 | B31: 46209 | C31: 46216 | D31: =MONTH(B31)&"月" | E31: 2 | F31: 07/06、07/13 | G31: 【梅田・少人数】取り残されないための実践AI活用ワークショップ|ChatGPT以外の生成AIも使い分け | H31: merit運営事務局 | J31: こくちーずプロ | K31: オフライン（会場） | L31: re:Dine 大阪府大阪市北区大深町6-38 グラングリーン大阪 北館 JAM BASE 1 階 | M31: 生産性向上・業務効率化 | N31: AIエージェント | O31: ○ | P31: 7 | Q31: 参加者数 | R31: 12 | S31: 全2回の合計 | T31: ※ご参加の方は、 申込完了メール より 「自己紹介シート」 の作成をお願いしております。必ずご確認頂くようお願い致します。 MERIT AI WORKSHOP AI活用ワークショップ ChatGPTだけじゃない、 主要AIの「使い分け」を90分で。 手を動かしながら、明日から使える実践スキルが身につく 「ChatGPTは使ってるけど、他のAIと何が違うの？」 「目的に合ったAIをちゃんと選べているか自信がない…」 その疑問を、 90分の | U31: https://www.kokuchpro.com/event/462c32654e8582dc98f1d8324a64443d/ | W31: 本文一致
A32: 31 | B32: 46210 | C32: 46239 | D32: =MONTH(B32)&"月" | E32: 2 | F32: 07/07、08/05 | G32: AIセキュリティ実践！最初に見るべき4つの領域 〜ID・ネットワーク・ログ・AI資産管理から考える〜 | H32: cloudace | J32: Doorkeeper | K32: 不明 | M32: 営業・マーケ・CS | N32: AIエージェント | O32: ○ | P32: 0 | Q32: 参加者数 | R32: 60 | S32: 全2回の合計 | T32: 【重要】本セミナーはdoorkeeperだけではお申し込み完了となりません。下記リンク先よりクラウドエースのwebサイトにてお申し込みをお願いいたします。 お申し込みはこちら https://cloud-ace.jp/event/260707/?utm_source=doorkeeper&utm_medium=referral 社内で生成AIやAIアシスタント（AIエージェント）の活用が進む中、「安全に使うための仕組みづくり」に悩む担 | U32: https://cloudace.doorkeeper.jp/events/197917 | W32: 本文一致
A33: 32 | B33: 46210 | C33: 46210 | D33: =MONTH(B33)&"月" | E33: 1 | G33: Devinの組織運用 - 開発現場での活用とガバナンス | H33: ファインディ／Findy | J33: connpass | K33: オンライン | L33: オンライン | M33: 開発生産性 | N33: AIエージェント | O33: ○ | P33: 234 | Q33: 参加者数 | U33: https://findy.connpass.com/event/396823/ | W33: タイトル一致
A34: 33 | B34: 46210 | C34: 46238 | D34: =MONTH(B34)&"月" | E34: 4 | F34: 07/07、07/21、07/28、08/04 | G34: Weekly Claude Code Live #9 | H34: ジェネラティブエージェンツ / Generative Agents | J34: connpass | K34: 会場 | L34: (場所未定) | M34: 開発生産性 | N34: AIエージェント | O34: ○ | P34: 93 | Q34: 参加者数 | S34: 全4回の合計 | U34: https://generative-agents.connpass.com/event/399060/ | W34: タイトル一致
A35: 34 | B35: 46210 | C35: 46210 | D35: =MONTH(B35)&"月" | E35: 1 | G35: 【7月7日開催｜無料ウェビナー】スマート製造における産業用AI：2026年の技術トレンドと実装課題 | H35: 株式会社グローバルインフォメーション | J35: ZDNET Japan イベント | K35: オンライン | L35: WEB | M35: 生産管理・製造・SCM | N35: AIエージェント | O35: ○ | Q35: 不明 | T35: 開催場所： WEB 開催日： 2026-07-07 市場調査レポートを販売する株式会社グローバルインフォメーションはドイツを本拠とする提携調査会社、IoT Analytics (IoTアナリティクス)社と共同で無料ウェビナー「スマート製造における産業用AI：2026年の技術トレンドと実装課題」を7月7日に開催いたします。 参加申し込み・詳細 ( リンク » ) ■セミナー概要 開催日：2026年7月7日(火) 開催時間：14:00～15 | U35: https://japan.zdnet.com/event_info/30014942/ | W35: 本文一致
A36: 35 | B36: 46210 | C36: 46232 | D36: =MONTH(B36)&"月" | E36: 1 | G36: 【松尾研発】「職人の勘」をデータ化する。AIエージェントによる不具合対応ナレッジの標準化と実践事例 | H36: 株式会社QuackShift | J36: TECH PLAY | K36: オンライン | M36: 生産性向上・業務効率化 | N36: AIエージェント | O36: ◎ | P36: 1 | Q36: 申込者数 | R36: 100 | T36: 【松尾研発】「職人の勘」をデータ化する。AIエージェントによる不具合対応ナレッジの標準化と実践事例 2026年7月29日（水）12:00-13:00 「不具合対応ナレッジの標準化とAIエージェント活用」をテーマに無料のオンラインセミナーを開催します！ 【イベント内容】 「あのトラブル、以前も起きた気がするが、どう対応したか分からない」 「熟練のAさんがいないと、設備の異常原因が特定できない」 「過去の報告書や修理記録はPDFやExcel | U36: https://techplay.jp/event/997993 | W36: タイトル一致
A37: 36 | B37: 46210 | C37: 46273 | D37: =MONTH(B37)&"月" | E37: 3 | F37: 07/07、08/04、09/08 | G37: 【生成AIベストプラクティス】上場企業15社以上で効果が!AI Agent型の導入で活用促進する施策 | H37: TechWorker | J37: connpass | K37: オンライン | L37: オンライン | M37: 技術・AI全般 | N37: AIエージェント | O37: ○ | P37: 15 | Q37: 参加者数 | S37: 全3回の合計 | U37: https://connpass.com/event/396661/ | W37: タイトル一致
A38: 37 | B38: 46210 | C38: 46210 | D38: =MONTH(B38)&"月" | E38: 1 | G38: 今こそ試したい Claude Cowork ⼊⾨②|AI集客を徹底解説 | H38: みんなシステムズ セミナー担当 | J38: こくちーずプロ | K38: オンライン | L38: オンライン 日本 | M38: 営業・マーケ・CS | N38: AIエージェント | O38: ◎ | P38: 2 | Q38: 参加者数 | R38: 30 | T38: セミナー情報 前回、満員御礼のClaude Cowork ⼊⾨。 今回はコンテンツ制作を軸として、「Claude Cowork」の活用事例をご紹介します。 プログラミング知識は不要。 ホームページ改善、ブログ記事作成、業務実績ページ作成の事例を元にClaude Coworkの活用事例をご紹介します。 このセミナーでお話しすること Claude Coworkを活用したホームページ改善事例 Claude Cowork×Excelによるブログ | U38: https://www.kokuchpro.com/event/06a414b82ca253edd78099fa5ac8a980/ | W38: タイトル一致
A39: 38 | B39: 46210 | C39: 46210 | D39: =MONTH(B39)&"月" | E39: 1 | G39: 実演で理解!AI-Claudeで創る、新しい仕事のカタチ。〜『AIに任せる』、未経験からの実践AX〜 | H39: （記載なし） | J39: こくちーずプロ | K39: オンライン | L39: オンライン 日本 | M39: 営業・マーケ・CS | N39: AIエージェント | O39: ○ | Q39: 不明 | T39: 話題の生成AI「Claude」を活用してみたいけど、 難しそうで、どう活用したら良いかわからない… そんなビジネスパーソンに向けて、AI「Claude」を取り巻く市場や企業課題を提示しながら具体的な活用方法を実演（デモンストレーション）を通じて、「Claude」を体験できるウェビナーを開催します。 ▶︎詳しくは こちら 今回は、観光業や宿泊業の業界が抱える「口コミ返信」の業務課題をテーマに、「Claude」を実演。 非IT企業でも、営業 | U39: https://www.kokuchpro.com/event/a79b4469b0d0538468ca8b3f0a02fe13/ | W39: 本文一致
A40: 39 | B40: 46211 | C40: 46293 | D40: =MONTH(B40)&"月" | E40: 13 | F40: 07/08、07/11、07/19、07/22、07/29、08/15、08/23、08/26、08/29、09/13、09/16、09/23、09/28 | G40: 0からのClaudeCodeによるAIエージェント入門セミナー | H40: データ分析ベーシック講座クラブ | J40: connpass | K40: オンライン | L40: オンライン | M40: 営業・マーケ・CS | N40: AIエージェント | O40: ◎ | P40: 36 | Q40: 参加者数 | R40: 130 | S40: 全13回の合計 | U40: https://data-analysis-basics.connpass.com/event/399367/ | W40: タイトル一致
A41: 40 | B41: 46211 | C41: 46211 | D41: =MONTH(B41)&"月" | E41: 1 | G41: AIで記録し、AIに聞く。i-Reporter×Dr.Sum×AIで変わる製造現場 | H41: （記載なし） | J41: ビジネス+IT | K41: online | L41: オンライン | M41: 生産管理・製造・SCM | N41: MCP | O41: ○ | Q41: 不明 | T41: 日報・点検・品質記録など、製造現場には膨大なデータが生まれ続けています。i-Reporterでは、Edge AIによるOCRやバーコード読み取りを活用することで、これらの現場記録をスピーディかつ正確にデジタル化することができます。しかし、「記録はできている、でもそのデータをAIに活かせていない」という課題を感じる企業が増えているのも現実です。 本セミナーでは、MCP対応を開始したデータ分析基盤Dr.Sumを活用し、複数システムのデータ統 | U41: https://www.sbbit.jp/eventinfo/89048 | W41: 本文一致
A42: 41 | B42: 46211 | C42: 46246 | D42: =MONTH(B42)&"月" | E42: 2 | F42: 07/08、08/12 | G42: AIミーティング 2026/07/08 #AIエージェント #MCP | H42: 大阪駆動開発 | J42: connpass | K42: オンライン | L42: オンライン | M42: 開発生産性 | N42: 両方 | O42: ○ | P42: 108 | Q42: 参加者数 | S42: 全2回の合計 | U42: https://osaka-driven-dev.connpass.com/event/396961/ | W42: タイトル一致
A43: 42 | B43: 46211 | C43: 46211 | D43: =MONTH(B43)&"月" | E43: 1 | G43: Agentforce活用を成功に導くSalesforceセキュリティとAIガバナンス最前線 ～自律型AI環境で顕在化する「ファイル・URL由来のサイバー脅威」の盲点～ | H43: ウィズセキュア株式会社 | I43: マジセミ株式会社 | J43: Doorkeeper | K43: 不明 | M43: 営業・マーケ・CS | N43: AIエージェント | O43: ◎ | P43: 5 | Q43: 参加者数 | R43: 8 | T43: 本セミナーはWebセミナーです ツールはZoomを使います。URLは直前にメールにてご連絡いたします。 なお、「osslabo.com」「majisemi.com」からのメールが迷惑メールとならないよう、メールの設定をご確認ください。 Agentforce導入がもたらす圧倒的な業務効率化と経営メリットとは Agentforceは、Salesforceが提供する自律型AIエージェント基盤として、営業やカスタマーサポート・マーケティングな | U43: https://majisemi-security.doorkeeper.jp/events/197735 | W43: タイトル一致
A44: 43 | B44: 46211 | C44: 46211 | D44: =MONTH(B44)&"月" | E44: 1 | G44: Claude Codeで開発効率をアップする！ ＜第2回＞勝手な動きで壊させない！ | H44: mnp-pr | J44: connpass | K44: オンライン | L44: オンライン | M44: 開発生産性 | N44: AIエージェント | O44: ○ | P44: 37 | Q44: 参加者数 | R44: 50 | U44: https://connpass.com/event/399507/ | W44: タイトル一致
A45: 44 | B45: 46211 | C45: 46255 | D45: =MONTH(B45)&"月" | E45: 4 | F45: 07/08、07/21、08/12、08/21 | G45: GA4×生成AI(Gemini)で 広がるデータ分析の新常識 〜探索レポートが苦手でもOK！ MCPサーバーで始める自然言語GA4分析〜 | H45: 株式会社シンメトリック | J45: TECH PLAY | K45: オンライン | M45: 営業・マーケ・CS | N45: MCP | O45: ◎ | Q45: 非公開 | R45: 120 | S45: 全4回の合計 | T45: GA4×生成AI(Gemini)で広がるデータ分析の新常識〜探索レポートが苦手でもOK！MCPサーバーで始める自然言語GA4分析〜 本セミナーの参加にはTechPlayでのお申込み後、開催15分前までにセミナー申し込みフォームへ必要事項をご記入いただく必要がございます。申し込みフォームへのリンクは申し込み完了メールに記載しております 参加費 無料 開催概要 本セミナーの参加にはTechPlayでのお申込み後、開催15分前までにセミナー申 | U45: https://techplay.jp/event/997571 | W45: タイトル一致
A46: 45 | B46: 46211 | C46: 46219 | D46: =MONTH(B46)&"月" | E46: 1 | G46: 「ブラウザ操作AIエージェント」で実現する、現場主導の業務効率化 | H46: 株式会社リンクレア | J46: ビジネス+IT | K46: online | L46: オンライン | M46: 生産性向上・業務効率化 | N46: AIエージェント | O46: ◎ | Q46: 不明 | T46: 「AIエージェントを活用して、社内の業務効率を一気に高めたい」 「現場が自走できる、新しい自動化の仕組みを取り入れたい」 生成AIの進化により、Webブラウザ上の業務を自律的に行う「AIエージェント」の実用化に向けた検証が進んでいます。 本ウェビナーでは、最新の「ブラウザ操作特化型AIエージェント」の技術動向と、現場主導で業務変革を起こすための方法について解説します。 事例をもとに、技術的な専門知識がない現場部門でも、これからの「業務自 | U46: https://www.sbbit.jp/eventinfo/89273 | W46: タイトル一致
A47: 46 | B47: 46211 | C47: 46211 | D47: =MONTH(B47)&"月" | E47: 1 | G47: 【エキスパート講座】AIエージェント構築｜コードゼロで業務を自動化するOpenClaw実践講座（2日間講座） | H47: 一般社団法人ウェブ解析士協会 講座企画運営部（担当：沖本一生） | J47: Doorkeeper | K47: 不明 | M47: 生産性向上・業務効率化 | N47: AIエージェント | O47: ◎ | P47: 3 | Q47: 参加者数 | T47: 講座概要 こちらの講座は、7/8（水）20:00～21:30、7/22（水）20:00～21:30 の２日間講座となります。 AIチャットは業務に活用している。でも「毎週の実績チェック」「GA4の数値確認」「クライアントへの定例レポート」等々、そういった繰り返しの作業は、まだ自分でやっていませんか？ この講座では、プログラミングなしでAIエージェントを構築できる「OpenClaw」の導入からあなたの実務に合わせた自動化ツールを完成させ | U47: https://web-mining.doorkeeper.jp/events/197628 | W47: タイトル一致
A48: 47 | B48: 46211 | C48: 46211 | D48: =MONTH(B48)&"月" | E48: 1 | G48: 【出版記念！ランチイベント】MastraによるAIエージェント開発運用実践入門 | H48: KDDIアジャイル開発センター / KAG | J48: connpass | K48: 会場 | L48: (場所未定) | M48: 開発生産性 | N48: AIエージェント | O48: ○ | P48: 57 | Q48: 参加者数 | U48: https://kddi-agile.connpass.com/event/395678/ | W48: タイトル一致
A49: 48 | B49: 46211 | C49: 46211 | D49: =MONTH(B49)&"月" | E49: 1 | G49: これからのサプライチェーンのあるべき姿を解説 キナクシス×JFEシステムズ ウェビナー | H49: キナクシス・ジャパン | J49: 個別調査（公式サイト・PR TIMES等） | K49: オンライン | M49: 生産管理・製造・SCM | N49: AIエージェント | O49: ◎ | Q49: 不明 | T49: 予測できない変化を前提に、AIエージェント技術で適応型サプライチェーンを実現する方法を、デモを交えて解説する。 | U49: https://www.jfe-systems.com/press/2026/20260616_news.html | W49: 個別確認
A50: 49 | B50: 46211 | C50: 46211 | D50: =MONTH(B50)&"月" | E50: 1 | G50: 応募数・定着率を同時に伸ばす「攻めと守り」のDX×採用戦略【無料ウェビナー】 | H50: 応募数・定着率を同時に伸ばす「攻めと守り」のDX×採用戦略【無料ウェビナー】事務局 | J50: こくちーずプロ | K50: オンライン | L50: オンライン 日本 | M50: 生産性向上・業務効率化 | N50: AIエージェント | O50: ○ | P50: 0 | Q50: 参加者数 | R50: 20 | T50: 「攻めと守り」のDX×採用戦略 〜内部効率化 × 採用ブランディングで応募数・定着率を同時に伸ばす攻守一体戦略〜 【このようなお悩みはありませんか？】 多くの企業が直面している「人手不足」という経営課題。 人材確保や業務効率化、組織の生産性向上は、いま多くの企業にとって重要なテーマとなっています。 その解決には、「DXによる業務の標準化・省力化」といった社内基盤の強化に加え、求職者の検索行動を踏まえた「風評被害対策・採用ブランディング」 | U50: https://www.kokuchpro.com/event/cde4ce2c4b7294f0c83ee873f871ae9c/ | W50: 本文一致
A51: 50 | B51: 46211 | C51: 46211 | D51: =MONTH(B51)&"月" | E51: 1 | G51: 金融機関における外部委託先管理・サードパーティリスク管理とITガバナンス・リスクの最前線 | H51: 株式会社セミナーインフォ（講師: DiGRIT Technologies株式会社 代表 鬼塚 智義 氏） | J51: セミナー情報.com | K51: 会場 / オンライン | M51: 生産性向上・業務効率化 | N51: AIエージェント | O51: ○ | Q51: 不明 | T51: (詳細ページは再配信ページへ転送: https://seminar-info.jp/entry/seminars/view/3/6886) ※本セミナーは2026/7/8に開催・収録したセミナーの リバイバル配信 です。 【本セミナーで得られること】 （例） ・金融機関に求められるITガバナンスの全体像と最新動向の体系的理解 ・サードパーティリスク管理（TPRM）の設計・運用ポイント ・AI・クラウド・PQCなど新興リスク領域への具体的 | U51: https://www.seminar-info.jp/entry/seminars/view/3/6845 | W51: 本文一致
A52: 51 | B52: 46212 | C52: 46212 | D52: =MONTH(B52)&"月" | E52: 1 | G52: Instagram・Threads×Claude Codeセミナー | H52: AIの学校 AI Crew事務局 | J52: こくちーずプロ | K52: オンライン | L52: オンライン 日本 | M52: 開発生産性 | N52: AIエージェント | O52: ○ | Q52: 不明 | T52: Instagram・Threads×Claude Code 業界激震セミナー Welcome to 新時代。 Instagram・Threads発信者の皆さま、お待たせしました。 これまで一人で頑張ってきたSNS運用を、これからは「AIチーム」と一緒に進める時代です。 今回のセミナーでは、みやっち‍が実際にInstagram・Threads運用をどのようにClaude Codeで自動化・仕組み化しているのかを、初めて一気に公開します。 | U52: https://www.kokuchpro.com/event/260709_claudecode/ | W52: タイトル一致
A53: 52 | B53: 46212 | C53: 46212 | D53: =MONTH(B53)&"月" | E53: 1 | G53: 【7月9日(木)開催】AI時代の品質保証は、上流工程で決まる！ ～仕様書・設計書レビューに必要な品質基準とAI活用～ | H53: バルテスグループ | J53: TECH PLAY | K53: オンライン | M53: 営業・マーケ・CS | N53: AIエージェント | O53: ○ | Q53: 非公開 | R53: 120 | T53: 開催概要 生成AIの活用は、ChatGPTやClaudeを個人が使用する段階から、AIエージェントを業務プロセスに組み込み、組織として活用する段階へ移行しつつあります。 開発プロジェクトにおいては、要件定義書・仕様書・設計書などの上流工程ドキュメントの品質が、後工程の不具合や手戻りに大きく影響します。一方で、これらのレビューは属人化しやすく、観点のばらつきや確認工数の不足が課題です。 本セミナーでは、AI時代に求められる品質保証の考え方 | U53: https://techplay.jp/event/997208 | W53: 本文一致
A54: 53 | B54: 46212 | C54: 46289 | D54: =MONTH(B54)&"月" | E54: 10 | F54: 07/09、07/16、07/23、07/30、08/13、08/20、08/27、09/03、09/17、09/24 | G54: なんもわからん人の論文読み会（AIエージェントの未来：Foundation Agents）#41 | H54: なんもわからん人の論文、書籍読み会 | J54: connpass | K54: オンライン | L54: オンライン | M54: 技術・AI全般 | N54: AIエージェント | O54: ○ | P54: 68 | Q54: 参加者数 | S54: 全10回の合計 | U54: https://wakaran-reading.connpass.com/event/398586/ | W54: タイトル一致
A55: 54 | B55: 46212 | C55: 46212 | D55: =MONTH(B55)&"月" | E55: 1 | G55: 松尾研はこうAIを制御するのか AIエージェントの精度を担保・改善する仕組みエージェントハーネスとは | H55: #Offers_DeepDive / オファーズ | J55: connpass | K55: オンライン | L55: オンライン | M55: 技術・AI全般 | N55: AIエージェント | O55: ○ | P55: 305 | Q55: 参加者数 | U55: https://offers-jp.connpass.com/event/396197/ | W55: タイトル一致
A56: 55 | B56: 46212 | C56: 46213 | D56: =MONTH(B56)&"月" | E56: 1 | G56: 製造業DXサミット2026〜AIとデータの時代へ動き始めた製造業の未来像〜 | H56: 日経クロステック（日経BP） | J56: 個別調査（公式サイト・PR TIMES等） | K56: オンライン | M56: 生産管理・製造・SCM | N56: AIエージェント | O56: ◎ | Q56: 不明 | T56: データとAIの活用による製造業DXがテーマ。システムをまたいで業務を支援するAIエージェントや、フィジカルAIのセッションがある。 | U56: https://events.nikkeibp.co.jp/event/2026/nxt0709/ | W56: 個別確認
A57: 56 | B57: 46213 | C57: 46213 | D57: =MONTH(B57)&"月" | E57: 1 | G57: 7/10(金)今からキャッチアップ「SalesforceインプリをAgentとやるってどんな感じ？」 | H57: namespace | J57: connpass | K57: 会場 | L57: 東京都江東区常盤2-5-2 常盤マンション1階テナント | M57: 営業・マーケ・CS | N57: AIエージェント | O57: ◎ | Q57: 不明 | U57: https://namespace.connpass.com/event/395095/ | W57: タイトル一致
A58: 57 | B58: 46213 | C58: 46213 | D58: =MONTH(B58)&"月" | E58: 1 | G58: AIエージェントキャッチアップ #83 - AgentSpace | H58: ジェネラティブエージェンツ / Generative Agents | J58: connpass | K58: オンライン | L58: オンライン | M58: 技術・AI全般 | N58: AIエージェント | O58: ○ | P58: 64 | Q58: 参加者数 | R58: 200 | U58: https://generative-agents.connpass.com/event/398435/ | W58: タイトル一致
A59: 58 | B59: 46213 | C59: 46213 | D59: =MONTH(B59)&"月" | E59: 1 | G59: Claude Code開発ノウハウ大公開スペシャル by クラスメソッド | H59: クラスメソッド株式会社 | J59: connpass | K59: 会場 | L59: 大阪府大阪市中央区伏見町3-6-3 三菱UFJ信託銀行大阪ビル8階 | M59: 開発生産性 | N59: AIエージェント | O59: ○ | P59: 520 | Q59: 参加者数 | U59: https://classmethod.connpass.com/event/395374/ | W59: タイトル一致
A60: 59 | B60: 46213 | C60: 46260 | D60: =MONTH(B60)&"月" | E60: 2 | F60: 07/10、08/26 | G60: ClaudeCodeMeetupOsaka vol.2 | H60: AIエージェントユーザー会（AIAU） | J60: connpass | K60: 会場 | L60: 〒530-0001 大阪府大阪市北区梅田3丁目1番3号 ノースゲートビルディング | M60: 営業・マーケ・CS | N60: AIエージェント | O60: ◎ | P60: 116 | Q60: 参加者数 | R60: 137 | S60: 全2回の合計 | U60: https://aiau.connpass.com/event/394831/ | W60: タイトル一致
A61: 60 | B61: 46213 | C61: 46213 | D61: =MONTH(B61)&"月" | E61: 1 | G61: RAGの限界を超える!MCPで実現する正確なAIデータ活用 | H61: スノーリーズ株式会社 セミナー事務局 | J61: こくちーずプロ | K61: オンライン | L61: オンライン 日本 | M61: 生産管理・製造・SCM | N61: MCP | O61: ◎ | Q61: 不明 | T61: AI活用は、いま大きな転換期を迎えています。 「AIを入れたのに、結局Excelで集計している」——そのままでいいですか？ 生成AIを試した多くの企業が、こんな現実に直面しています。 RAGを導入したが、数値の回答が信用できず人手でチェックが発生 レポート作成のためにシステムからデータを抽出する作業が毎月続く AIに社内データを連携させたいが、やり方がわからず止まっている その原因は、ツールの問題ではなくAIとデータの"つなぎ方"にあり | U61: https://www.kokuchpro.com/event/74c3aed9a16d9d1838ba976b1b7a5170/3830827/ | W61: タイトル一致
A62: 61 | B62: 46213 | C62: 46213 | D62: =MONTH(B62)&"月" | E62: 1 | G62: 【エキスパート講座】実務で差がつく！生成AIアウトプット実践・比較マスター講座（2日間講座） | H62: 一般社団法人ウェブ解析士協会 講座企画運営部（担当：沖本一生） | J62: Doorkeeper | K62: 不明 | M62: 営業・マーケ・CS | N62: AIエージェント | O62: ○ | P62: 0 | Q62: 参加者数 | T62: 講座概要 こちらの講座は、7/10（金）13:00～14:30、7/17（金）13:00～14:30 の２日間講座となります。 本講座は、生成AIを単なる「検索ツール」や「要約ツール」としてではなく、Webマーケティング実務における「優秀なアシスタント」としてフル活用するための実践型ワークショップです。 世の中には多数の生成AI（ChatGPT、Claude、Geminiなど）が存在しますが、実はそれぞれ「得意なアウトプット」が異なり | U62: https://web-mining.doorkeeper.jp/events/197927 | W62: 本文一致
A63: 62 | B63: 46213 | C63: 46213 | D63: =MONTH(B63)&"月" | E63: 1 | G63: 【大阪・北浜】SES×AI活用開発交流会|案件を探す会社・人材を探す会社・開発を依頼したい会社が集まる交流会 | H63: 株式会社ユニオン | J63: こくちーずプロ | K63: オフライン（会場） | L63: 北浜BASE 大阪府大阪市中央区伏見町2-2-10 谷ビル5F | M63: 開発生産性 | N63: AIエージェント | O63: △ | Q63: 不明 | T63: いま、AIの急速な進化により、システム開発業界は大きな転換期を迎えています。 そして、多くの企業も次のような課題を抱えています。 開発案件はあるが開発人材が足りない 優秀なエンジニア人材はいるが案件が不足している システムやAIを導入したいが、誰に相談すればよいかわからない 信頼できる開発会社や協業先を探している AIを活用した新しいビジネスを模索している そこで今回、 「案件を探す会社」 「人材を探す会社」 「開発を発注したい会社」 | U63: https://www.kokuchpro.com/event/union710/ | W63: 本文一致
A64: 63 | B64: 46213 | C64: 46213 | D64: =MONTH(B64)&"月" | E64: 1 | G64: インフラ作業を生成AI（ClaudeCode）にどこまで任せるか | H64: Scalar | J64: connpass | K64: オンライン | L64: オンライン | M64: 営業・マーケ・CS | N64: AIエージェント | O64: ◎ | P64: 28 | Q64: 参加者数 | R64: 100 | U64: https://scalar.connpass.com/event/399339/ | W64: タイトル一致
A65: 64 | B65: 46213 | C65: 46213 | D65: =MONTH(B65)&"月" | E65: 1 | G65: ランサムに狙われるVPN、パッチ対応を少人数情シスで抱え続けるのはもう限界？ 〜VPNとZTNAの併存運用で、業務を止めずに段階的に手放す方法〜 | H65: 三信電気株式会社 シスコシステムズ合同会社 | I65: 三信電気株式会社 シスコシステムズ合同会社 | J65: Doorkeeper | K65: 不明 | M65: 生産性向上・業務効率化 | N65: AIエージェント | O65: ○ | P65: 0 | Q65: 参加者数 | T65: 本セミナーはWebセミナーです ツールはZoomを使います。URLは直前にメールにてご連絡いたします。 なお、「osslabo.com」「majisemi.com」からのメールが迷惑メールとならないよう、メールの設定をご確認ください。 ランサム攻撃で狙われるVPN機器 ランサムウェア被害が深刻化する今、多くの企業で最大の「侵入経路」となっているのがVPN機器です。クラウド活用が進む一方で、「社内システムへのアクセスのために、古いオンプ | U65: https://majisemi-security.doorkeeper.jp/events/197789 | W65: 本文一致
A66: 65 | B66: 46213 | C66: 46213 | D66: =MONTH(B66)&"月" | E66: 1 | G66: 社内システム × AI連携「MCP」入門 今日から使える業務効率化の新常識 | H66: スノーリーズ株式会社 セミナー事務局 | J66: こくちーずプロ | K66: オンライン | L66: オンライン 日本 | M66: 生産性向上・業務効率化 | N66: 両方 | O66: ◎ | Q66: 不明 | T66: 「また同じ質問が来た」「どこに情報があるかわからない」 その日常、実は仕組みで解決できます。 人手不足の今、問合せ対応に課題を抱えている企業は多い！ 問い合わせ対応の現場では、膨大な履歴・散在する情報・担当者ごとの回答のバラつきが積み重なり、日々の業務を圧迫しています。 その根本原因は、社内の情報がAIとつながっていないことにあります。 本セミナーでは、「AIエージェント＋MCP連携」という最新アプローチにより、社内データと生成AIをつ | U66: https://www.kokuchpro.com/event/30e777371171a23e6946ba9b829e6469/3830837/ | W66: タイトル一致
A67: 66 | B67: 46213 | C67: 46241 | D67: =MONTH(B67)&"月" | E67: 2 | F67: 07/10、08/07 | G67: 第2回 やさしいClaude Code LT大会 | H67: やさしいAI駆動社会クリエイターズ | J67: connpass | K67: オンライン | L67: オンライン | M67: 開発生産性 | N67: AIエージェント | O67: ○ | P67: 135 | Q67: 参加者数 | S67: 全2回の合計 | U67: https://biosbootcamp.connpass.com/event/396378/ | W67: タイトル一致
A68: 67 | B68: 46213 | C68: 46213 | D68: =MONTH(B68)&"月" | E68: 1 | G68: ＜金融AI2026＞自律型AI時代の金融実務再設計と組織の処方箋～失敗の本質とX世代再活性化によるAIベストプラクティス～ | H68: （記載なし） | J68: セミナー情報.com | K68: 会場 / オンライン | M68: 技術・AI全般 | N68: AIエージェント | O68: ○ | Q68: 不明 | U68: https://www.seminar-info.jp/entry/seminars/view/3/6868 | W68: タイトル一致
A69: 68 | B69: 46214 | C69: 46214 | D69: =MONTH(B69)&"月" | E69: 1 | G69: AIの力で技術負債を解消しよう 〜仕様書ゼロのレガシーコードを、Claude＋Tsumikiでどう攻略する？〜 | H69: 株式会社くすりの窓口 | J69: TECH PLAY | K69: オンライン | M69: 開発生産性 | N69: AIエージェント | O69: △ | P69: 9 | Q69: 申込者数 | R69: 30 | T69: こんなコード、開くのが怖くなっていませんか？ ・触ると壊れそうで、誰も手をつけられない「秘伝のタレ」化したコード ・書いた本人はもういない。仕様書は、ない。 ・「たぶんこう動いてるはず…」で運用され続けているシステム 技術負債の中でも一番やっかいなのが、仕様書が存在しないコードです。直したいけど、何が正解かわからない。だから触れない。そして負債は静かに膨らみ続けます。 【この勉強会でやること】 そんな「仕様書なき技術負債」に、Claud | U69: https://techplay.jp/event/997810 | W69: 本文一致
A70: 69 | B70: 46214 | C70: 46214 | D70: =MONTH(B70)&"月" | E70: 1 | G70: Claude Coworkで作る"自由に編集できる"スライド作成 | H70: デジタルレイバーズ | J70: connpass | K70: オンライン | L70: オンライン | M70: 技術・AI全般 | N70: AIエージェント | O70: ○ | P70: 26 | Q70: 参加者数 | R70: 30 | U70: https://digital-labors.connpass.com/event/398250/ | W70: タイトル一致
A71: 70 | B71: 46214 | C71: 46214 | D71: =MONTH(B71)&"月" | E71: 1 | G71: ゼロから学べる!AI活用術(実践編) | H71: 株式会社タスクールPlus | J71: こくちーずプロ | K71: オフライン（会場） | L71: タスクール 愛知県名古屋市千種区千種通7-25-1 サンライズ千種502 | M71: 生産性向上・業務効率化 | N71: AIエージェント | O71: ○ | P71: 0 | Q71: 参加者数 | R71: 10 | T71: 【7/11（土）開催｜ゼロから学べる！AI活用術 実践編】 「ChatGPTは少し使えるようになった」 「でも、仕事にどう活かせばいいのか分からない」 「毎回プロンプトを書くのが面倒で、結局続かない」 「AIを使っているつもりだけど、成果につながっている実感がない」 そんな方に向けて、AI活用講座の実践編を開催します。 今回のテーマは、AIを“思考の伴走者”から“業務の共同作業者”へ育てること。 入門編では、ChatGPTを中心に、AI | U71: https://www.kokuchpro.com/event/7fa5a272404e3a707e160fa8264c6f28/ | W71: 本文一致
A72: 71 | B72: 46215 | C72: 46215 | D72: =MONTH(B72)&"月" | E72: 1 | G72: Claude Codeで考える AI駆動開発のしくみづくりワークショップ | H72: AI駆動開発(AI-Driven Development) | J72: connpass | K72: 会場 | L72: 〒160-0023 東京都新宿区西新宿7-20-1住友不動産西新宿ビル 32F | M72: 開発生産性 | N72: AIエージェント | O72: ○ | Q72: 不明 | U72: https://aid.connpass.com/event/397707/ | W72: タイトル一致
A73: 72 | B73: 46215 | C73: 46215 | D73: =MONTH(B73)&"月" | E73: 1 | G73: Claude Code勉強会 @STATION Ai 名古屋 | H73: anzi_kosaka | J73: connpass | K73: 会場 | L73: (場所未定) | M73: 開発生産性 | N73: AIエージェント | O73: ○ | P73: 5 | Q73: 参加者数 | U73: https://connpass.com/event/399282/ | W73: タイトル一致
A74: 73 | B74: 46215 | C74: 46232 | D74: =MONTH(B74)&"月" | E74: 2 | F74: 07/12、07/29 | G74: 【参加無料】非エンジニアのためのClaude Code活用超入門 | H74: 和から株式会社 | J74: TECH PLAY | K74: オンライン | M74: 生産性向上・業務効率化 | N74: AIエージェント | O74: ◎ | P74: 11 | Q74: 申込者数 | R74: 25 | S74: 全2回の合計 | T74: Claude Codeはあなたの業務でも使えます 「Claude Codeが話題らしい」「なんか便利そう」——そう聞いて気になってはいるものの、**「どうせエンジニア向けのツールでしょ」「プログラミングができない自分には関係ない」と一歩引いていませんか。Claude Codeとは、ファイルの作成・整理・編集といった作業を自動でこなしてくれるAIツールです。ふだん使っているChatGPTやGeminiが「質問に答えてくれるAI」だとすれば | U74: https://techplay.jp/event/997912 | W74: タイトル一致
A75: 74 | B75: 46216 | C75: 46216 | D75: =MONTH(B75)&"月" | E75: 1 | G75: Claude Codeで「AI社員」を採用・配置する方法|経営者向け無料セミナー | H75: Claude Codeで「AI社員」を採用・配置する方法|経営者向け無料セミナー事務局 | J75: こくちーずプロ | K75: オンライン | L75: オンライン 日本 | M75: 生産性向上・業務効率化 | N75: AIエージェント | O75: ◎ | P75: 4 | Q75: 参加者数 | R75: 30 | T75: 「あと1人いれば回るのに」——そう思ったこと、ありませんか？ 採用すれば年間300〜500万円。派遣を頼んでも月20〜30万円。でも、そこまでの余裕はない。 Claude Codeなら、月3000円からで「AI社員」を配置できます。営業・マーケ・経理——それぞれの業務に特化したAIを、自分で作って、自分で育てる。今回は、そのAI社員を実際にゼロから作る過程をライブでお見せします。 ■こんなこと、ありませんか？ ・「AI社員」「AIエージ | U75: https://www.kokuchpro.com/event/53069532975ddcdbf3d1a3e8d44d7350/ | W75: タイトル一致
A76: 75 | B76: 46216 | C76: 46216 | D76: =MONTH(B76)&"月" | E76: 1 | G76: 【Flashセミナー Vol.154】｢人だけ｣の参加お断り 『Claude Code』がEC施策を学ぶ60分 | H76: web-mining | J76: Doorkeeper | K76: 不明 | M76: 営業・マーケ・CS | N76: AIエージェント | O76: ◎ | P76: 116 | Q76: 参加者数 | R76: 250 | T76: こちらのセミナーは「参加要件」がございます。 必ずお読みください。 セミナー内容 ECの改善、計測も、商品ページも、SEOも、ぜんぶ自分。気づけば施策はやりっ放し——多くのEC担当者がこんな状況に陥っているのではないでしょうか。 なぜなら、施策を進めるのも自分、学ぶのも自分。なんなら発送だって自分が担当。 もう“自分自分”なEC運営、やめませんか？ このセミナーでご紹介するのは、食品・お酒・製造業など、業種の異なる複数のECサイトで、 | U76: https://web-mining.doorkeeper.jp/events/198040 | W76: タイトル一致
A77: 76 | B77: 46216 | C77: 46216 | D77: =MONTH(B77)&"月" | E77: 1 | G77: 【与信DX】公開情報が少ない企業も、AIエージェントが見抜く時代へ | H77: Baseconnect株式会社（協力：マジセミ株式会社） | J77: マジセミ | K77: online | L77: オンライン | M77: 生産性向上・業務効率化 | N77: AIエージェント | O77: ◎ | Q77: 不明 | T77: ■中小・零細企業の与信判断が難しくなる 企業間取引では、新規取引先の信用力や反社・コンプライアンス上の懸念を確認したうえで、取引可否を判断することが求められます。ところが、中小・零細企業は公開されている財務情報やニュース、信用情報が限られることも多く、判断材料が十分に揃わないケースがあります。取引先の裾野が広がるほど確認対象も増えるため、限られた情報の中でいかに公平で再現性のある与信判断を行うかが、企業にとって大きな課題になっています。 | U77: https://prtimes.jp/main/html/rd/p/000005369.000054842.html | W77: タイトル一致
A78: 77 | B78: 46217 | C78: 46217 | D78: =MONTH(B78)&"月" | E78: 1 | G78: Alteryx on Tour : Tokyo | H78: アルテリックス・ジャパン合同会社 | J78: ビジネス+IT | K78: offline | L78: 東京都 | M78: 生産性向上・業務効率化 | N78: AIエージェント | O78: ○ | Q78: 不明 | T78: AI活用が活発になる中、その成果を左右するのはAIそのものではなく、信頼できるデータです。Alteryx on Tour : Tokyo では、 "Agentic Analytics Starts Here ~エージェンティック・アナリティクスが導くAI時代のデータ活用~" をテーマに、データの質を確保しながら、どのようにガバナンスを確立すべきか。そして、ビジネス部門が主体的に「データ活用」「自動化」「AI実装」にチャレンジするための環 | U78: https://www.sbbit.jp/eventinfo/88821 | W78: 本文一致
A79: 78 | B79: 46217 | C79: 46217 | D79: =MONTH(B79)&"月" | E79: 1 | G79: SoftBank World 2026「AX for Japan」 | H79: ソフトバンク | J79: 個別調査（公式サイト・PR TIMES等） | K79: ハイブリッド | L79: ライブ配信・会場展示（オンデマンド配信は7/21〜8/31） | M79: 大型カンファレンス・展示会 | N79: AIエージェント | O79: ◎ | Q79: 不明 | T79: 孫正義氏が「2040年に100兆個のAIエージェント」と講演した。自律型AIやフィジカルAIを紹介し、安川電機のロボットを展示した。 | U79: https://www.softbank.jp/corp/news/press/sbkk/2026/20260518_01/ | V79: https://k-tai.watch.impress.co.jp/docs/news/2109522.html | W79: 個別確認
A80: 79 | B80: 46217 | C80: 46217 | D80: =MONTH(B80)&"月" | E80: 1 | G80: TypeScriptで開発するAIエージェントの裏側 〜KAG社の実践知から学ぶMastra〜 | H80: ファインディ／Findy | J80: connpass | K80: オンライン | L80: オンライン | M80: 開発生産性 | N80: AIエージェント | O80: ○ | P80: 273 | Q80: 参加者数 | U80: https://findy.connpass.com/event/396881/ | W80: タイトル一致
A81: 80 | B81: 46217 | C81: 46217 | D81: =MONTH(B81)&"月" | E81: 1 | G81: ※NTTDATA、三菱UFJ銀行登壇!【データ活用に関する大規模カンファレンスを赤坂で開催します!】Alteryx on tour2025 | H81: アルテリックスジャパン | J81: こくちーずプロ | K81: オフライン（会場） | L81: 赤坂インターシティコンファレンス 東京都東京都港区赤坂1-8-1 赤坂インターシティAIR 3F・4F | M81: 技術・AI全般 | N81: AIエージェント | O81: △ | P81: 0 | Q81: 参加者数 | R81: 800 | T81: Alteryx on Tour Tokyo 7/14（火）10:00より、赤坂インターシティコンファレンスにて開催いたします。 今回は "Agentic Analytics Starts Here" をテーマに、 AGC、出光興産、大日本印刷、日揮グローバル、日本触媒、三井住友銀行、三菱UFJ銀行等、各社の事例登壇や野口竜司氏による特別講演がございます。 全セッション終了後にネットワーキングタイムがございますので登壇者の方や参加者の皆様 | U81: https://www.kokuchpro.com/event/1699adb0baf47e1ec210c620530b609e/3820023/ | W81: 本文一致
A82: 81 | B82: 46217 | C82: 46217 | D82: =MONTH(B82)&"月" | E82: 1 | G82: 【2026年版】人事DXの壁を突破!「AIエージェント、何に使うべき?」を解決 人事業務を変える鍵は「ワークフロー×AI」 | H82: ヒューマンリソシア株式会社 DXセミナー事務局 | J82: こくちーずプロ | K82: オンライン | L82: オンライン 日本 | M82: 生産性向上・業務効率化 | N82: AIエージェント | O82: ◎ | Q82: 不明 | T82: 「生成AIを導入したのに、思ったほど業務が減らない」 「RPAは入れたが、結局“人がつなぐ作業”が残っている」 多くの企業では、ChatGPTなどの生成AI活用が “メール作成”や“文章要約”など個人作業の効率化に留まり、 採用・労務・社内問い合わせ対応といった人事全体の業務改革にはつながっていません。 特に、人事各種システム、媒体、チャット、カレンダーなど 複数ツールをまたぐ作業や関係者との調整などは、 依然として人手に依存し、人事部 | U82: https://www.kokuchpro.com/event/tunagiai_260714/ | W82: タイトル一致
A83: 82 | B83: 46217 | C83: 46217 | D83: =MONTH(B83)&"月" | E83: 1 | G83: 【エキスパート講座】非エンジニアのためのCodex業務自動化・実践講座（2日間講座） | H83: 一般社団法人ウェブ解析士協会 講座企画運営部（担当：沖本一生） | J83: Doorkeeper | K83: 不明 | M83: 生産性向上・業務効率化 | N83: AIエージェント | O83: ◎ | P83: 7 | Q83: 参加者数 | T83: 講座概要 こちらの講座は、7/14（火）14:00～15:30、7/21（火）14:00～15:30 の２日間講座となります。 本講座は、AIを「チャット（対話）」として使う段階から卒業し、自律的に動く「エージェント（実行）」として使いこなすための実践型プログラムです。 最新のCodexを優秀なデジタルアシスタントとして迎え入れ、スライド作成、データ分析、コンテンツの量産、さらにはWebサイトの構築までを「自然言語の指示（プロンプト） | U83: https://web-mining.doorkeeper.jp/events/197998 | W83: タイトル一致
A84: 83 | B84: 46217 | C84: 46217 | D84: =MONTH(B84)&"月" | E84: 1 | G84: 改めて理解する「CrowdStrike」とは？ ～1つのプラットフォームで実現する最高峰のセキュリティ～ | H84: 株式会社マクニカ | J84: ZDNET Japan イベント | K84: オンライン | L84: WEB | M84: 技術・AI全般 | N84: AIエージェント | O84: △ | Q84: 不明 | T84: 開催場所： WEB 開催日： 2026-07-14 「ランサムウェアや未知の攻撃に、今の対策で本当に大丈夫か不安」 「セキュリティ製品が増えすぎて、管理が追いつかない」 これらの課題を解決するのが、1エージェント・1コンソールで業界最高峰のセキュリティを実現する次世代EDR「CrowdStrike」です。 本セミナーでは、2013年より10年以上、CrowdStrike社の国内No.1*代理店として活動しているマクニカが、製品の全体像か | U84: https://japan.zdnet.com/event_info/30014951/ | W84: 本文一致
A85: 84 | B85: 46218 | C85: 46218 | D85: =MONTH(B85)&"月" | E85: 1 | G85: 7/15(水) 16:00-【大好評セミナーを再配信！】 Copilot Studio活用の壁は「役割分担」で越える。 現場任せにせず、PoCを実務レベルへ引き上げる成功法則ポイント | H85: skillupai | J85: Doorkeeper | K85: オンライン | M85: 生産性向上・業務効率化 | N85: AIエージェント | O85: ◎ | P85: 0 | Q85: 参加者数 | R85: 30 | T85: ■ プログラム概要 多くの企業がMicrosoft 365 Copilotを導入し、Copilot StudioによるPoCに取り組み始めています。しかし、いざ実務に投入しようとすると「期待した回答が返ってこない」「社内システムとの連携がうまくいかない」といった壁に直面し、プロジェクトが停滞してしまうケースが少なくありません。 本セミナーでは、AIエージェントを「PoC」で終わらせず、「実務の即戦力」へと引き上げるためのポイントを解説 | U85: https://skillupai.doorkeeper.jp/events/197871 | W85: タイトル一致
A86: 85 | B86: 46218 | C86: 46218 | D86: =MONTH(B86)&"月" | E86: 1 | G86: AI Ready組織を見据えた データ基盤戦略とは～～IVRy＆アイスタイルが語る リアーキテクチャのリアル～～ | H86: Findy/ファインディ | J86: TECH PLAY | K86: オンライン | M86: 生産性向上・業務効率化 | N86: AIエージェント | O86: ○ | P86: 31 | Q86: 申込者数 | R86: 200 | T86: 📹アーカイブ動画 アーカイブ動画はこちらから <過去開催回> 過去開催 Data Career Talk (DCT)シリーズイベント 🚪 ※アーカイブ動画の閲覧にはFindyへの会員登録が必要です。ご了承ください。 第1回 「事業成長を牽引する全社横断データ組織とは？～Sansan&イオンスマートテクノロジーに聞くデータエンジニアの働き方～」 第2回 「AIエージェントを支えるデータエンジニアの仕事〜メルカリ＆ZOZOの実践〜」 第3回 | U86: https://techplay.jp/event/997557 | W86: 本文一致
A87: 86 | B87: 46218 | C87: 46218 | D87: =MONTH(B87)&"月" | E87: 1 | G87: AIが脆弱性を見つける時代、何を優先的に守るべきか？ ～攻撃者視点でリスクを見て、防御対象を見極める～ | H87: KELA株式会社 | I87: マジセミ株式会社 | J87: Doorkeeper | K87: 不明 | M87: 営業・マーケ・CS | N87: AIエージェント | O87: ○ | P87: 0 | Q87: 参加者数 | T87: 本セミナーはWebセミナーです ツールはZoomを使います。URLは直前にメールにてご連絡いたします。 なお、「osslabo.com」「majisemi.com」からのメールが迷惑メールとならないよう、メールの設定をご確認ください。 AIによって脆弱性発見が加速し、攻撃対象の発見も加速している現実 近年、生成AIやAIエージェントの進化により、脆弱性の発見や調査はかつてないスピードで行われるようになりました。 しかし、本当に警戒すべ | U87: https://majisemi-security.doorkeeper.jp/events/197893 | W87: 本文一致
A88: 87 | B88: 46218 | C88: 46218 | D88: =MONTH(B88)&"月" | E88: 1 | G88: AIエージェント × 感情AI SaaSの利活用とは～会議録・報告書をAIで活用し、プロジェクト課題を見つける方法～ | H88: 株式会社ジール イベント・セミナー事務局 | J88: TECH PLAY | K88: オンライン | M88: 生産性向上・業務効率化 | N88: AIエージェント | O88: ◎ | P88: 4 | Q88: 申込者数 | R88: 20 | T88: AIエージェント × 感情AI SaaSの利活用とは～会議録・報告書をAIで活用し、プロジェクト課題を見つける方法～ 概要 生成AIを活用したデータ分析や業務効率化の重要性が急速に高まる中、 「自社に合った活用方法がわからない」 「生成AIを活用した業務アプリケーション導入にハードルを感じる」 「AIをどの業務に適用すべきか、具体的なイメージが持てない」 「会議録や報告書、プロジェクト情報が蓄積されているものの、改善活動に活かしきれてい | U88: https://techplay.jp/event/997092 | W88: タイトル一致
A89: 88 | B89: 46218 | C89: 46218 | D89: =MONTH(B89)&"月" | E89: 1 | G89: AI活用の成果は“導入前の設計”でほぼ決まる | H89: 株式会社マイクロメイツ | J89: TECH PLAY | K89: オンライン | M89: 生産性向上・業務効率化 | N89: AIエージェント | O89: ○ | P89: 10 | Q89: 申込者数 | R89: 50 | T89: AI活用の成果は“導入前の設計”でほぼ決まる ～迷わず成果につなげるための「業務棚卸し・可視化」最短ルート～ 開催日 2026年7月15日（水）12：10〜12：40 12：00から入室可能 概要 AIエージェントの導入や活用を検討するなかで、 **「思ったほど効果が出ない」「どの業務に適用すべきか判断が難しい」**──そのようなお悩みはありませんか。 本セミナーでは、RPA導入事例をもとに、業務の一部を自動化しても全体の改善につながら | U89: https://techplay.jp/event/997980 | W89: 本文一致
A90: 89 | B90: 46218 | C90: 46219 | D90: =MONTH(B90)&"月" | E90: 1 | G90: CC AI BENCHMARK 2026（2Daysオンラインカンファレンス） | H90: 株式会社Edge Works | I90: コンタクトセンター向けAI企業20社 | J90: 個別調査（公式サイト・PR TIMES等） | K90: オンライン | L90: Zoom Webinar | M90: 営業・マーケ・CS | N90: AIエージェント | O90: ◎ | P90: 500 | Q90: 申込数 | S90: 告知時点で「申込500名突破」（各日の定員は1,000名） | T90: コンタクトセンター向けAIサービス20社を2日間で比較する無料カンファレンス。ベンチマークレポートの配布もある。 | U90: https://prtimes.jp/main/html/rd/p/000000006.000163625.html | W90: 個別確認 | X90: CS・コンタクトセンター領域
A91: 90 | B91: 46218 | C91: 46219 | D91: =MONTH(B91)&"月" | E91: 1 | G91: Fujitsu Experience Day 2026 | H91: 富士通 | J91: 個別調査（公式サイト・PR TIMES等） | K91: 会場 | L91: TAKANAWA GATEWAY Convention Center | M91: 大型カンファレンス・展示会 | N91: AIエージェント | O91: ◎ | Q91: 不明 | T91: 自己進化型マルチAIエージェントや、店舗・在庫向けのAIエージェントなど、44の技術・ソリューションを展示した。 | U91: https://cloud.watch.impress.co.jp/docs/event/2125529.html | W91: 個別確認
A92: 91 | B92: 46218 | C92: 46220 | D92: =MONTH(B92)&"月" | E92: 1 | G92: TECHNO-FRONTIER 2026（製造業向け生成AI展を新設） | H92: 日本能率協会 | J92: 個別調査（公式サイト・PR TIMES等） | K92: 会場 | L92: 東京ビッグサイト西展示棟 | M92: 生産管理・製造・SCM | N92: AIエージェント（生成AI中心） | O92: ◎ | P92: 33637 | Q92: 来場者数 | T92: 生成AI、スマートファクトリーDX、FA・ロボット、OTセキュリティなどを展示した。出展は440社・842小間。 | U92: https://jma-news.com/archives/7037 | W92: 個別確認 | X92: AIエージェントとしての打ち出しは弱い
A93: 92 | B93: 46218 | C93: 46218 | D93: =MONTH(B93)&"月" | E93: 1 | G93: 【30分・航空DX/AX】航空業界の属人化・引き継ぎ・例外対応を30分でAX化する 現場に定着するAIエージェント「OpenClaw AX」実践ウェビナー | H93: Ragate株式会社 | J93: TECH PLAY | K93: オンライン | M93: 生産性向上・業務効率化 | N93: AIエージェント | O93: ◎ | Q93: 非公開 | R93: 50 | T93: イベント概要 航空需要の回復、人手不足、運航・整備・地上支援業務の複雑化が進むなか、航空業界では「安全性」「定時性」「顧客体験」を維持しながら、現場と本部の業務負荷をどう下げるかが重要なテーマになっています。 一方で、日々の現場には、運航・整備・地上支援に関する過去事例の検索、手順書・マニュアル確認、申し送り、問い合わせ対応、報告書作成、Excel・管理台帳への転記といったデスクワークが多く残っています。業務システムやナレッジは存在して | U93: https://techplay.jp/event/997013 | W93: タイトル一致
A94: 93 | B94: 46218 | C94: 46218 | D94: =MONTH(B94)&"月" | E94: 1 | G94: 【7/15開催】仕事を減らして成果を増やす「AI社員」の作り方 入門|つながる交流勉強会 | H94: クロストーク | J94: こくちーずプロ | K94: オフライン（会場） | L94: Moccoハナレ2階セミナールーム 兵庫県姫路市南町33 2F | M94: 生産性向上・業務効率化 | N94: AIエージェント | O94: ○ | P94: 18 | Q94: 参加者数 | R94: 20 | T94: ChatGPTなどのチャットAIを使ってみたものの、 「結局、質問するだけで終わっている」 「業務効率化にどうつなげればいいかわからない」 「AIエージェントって最近よく聞くけど、何が違うの？」 そんな方に向けた、初心者にもわかりやすいAI活用入門セミナーです。 今回のテーマは、 “相談相手としてのAI”から、“業務を任せるAI社員”へ。 ChatGPTなどのチャットAIと、Claude Code / CodexなどのAIエージェントの | U94: https://www.kokuchpro.com/event/ffd85486629ca5f8cedca3e74e382492/ | W94: 本文一致
A95: 94 | B95: 46218 | C95: 46218 | D95: =MONTH(B95)&"月" | E95: 1 | G95: 【7月15日（水）無料オンラインセミナー】「バズ狙い」はもう終わり？ マーケティング担当者のためのAIエージェント活用 | H95: ソニーネットワークコミュニケーションズ株式会社、ＡＲアドバンストテクノロジ株式会社 | J95: PR TIMES | K95: online | L95: オンライン（Zoom） | M95: 営業・マーケ・CS | N95: AIエージェント | O95: ◎ | Q95: 不明 | T95: ＡＲアドバンストテクノロジ株式会社（本社：東京都渋谷区、代表取締役社長：武内 寿憲、以下ARI）とソニーネットワークコミュニケーションズ株式会社（本社：東京都品川区）は、2026年7月15日（水）、無料Webセミナー「「バズ狙い」はもう終わり？マーケティング担当者のためのAIエージェント活用〜ファンの熱量を資産に変える仕組みとは？〜」を共催いたします。 新規顧客獲得コストが高騰し、広告やバズ頼みの施策だけでは持続的な成長が難しくなってい | U95: https://prtimes.jp/main/html/rd/p/000000124.000066765.html | W95: タイトル一致
A96: 95 | B96: 46218 | C96: 46218 | D96: =MONTH(B96)&"月" | E96: 1 | G96: 【Claude Code】並行開発、どう回してる？ 鹿野さんに聞く 私の推しの並行開発環境 大公開 | H96: #Offers_DeepDive / オファーズ | J96: connpass | K96: オンライン | L96: オンライン | M96: 開発生産性 | N96: AIエージェント | O96: ○ | P96: 488 | Q96: 参加者数 | U96: https://offers-jp.connpass.com/event/395255/ | W96: タイトル一致
A97: 96 | B97: 46218 | C97: 46218 | D97: =MONTH(B97)&"月" | E97: 1 | G97: 【Flashセミナー Vol.156】AIは「道具」から「チームメイト」へ ひとりユニコーン経営 | H97: web-mining | J97: Doorkeeper | K97: 不明 | M97: 生産性向上・業務効率化 | N97: MCP | O97: ○ | P97: 96 | Q97: 参加者数 | R97: 250 | T97: こちらのセミナーは「参加要件」がございます。 必ずお読みください。 セミナー内容 2026年、生成AIは便利な道具から「自ら考え、計画し、実行する同僚」へと進化しました。Claude Cowork、ChatGPT Codex、Google Antigravityの3大プラットフォームが整い、AIに業務をまるごと任せる経営が現実になりつつあります。 一方で多くの経営者は、どのプラットフォームを、何から使うかの入り口で足を止めています。 | U97: https://web-mining.doorkeeper.jp/events/197930 | W97: 本文一致
A98: 97 | B98: 46218 | C98: 46218 | D98: =MONTH(B98)&"月" | E98: 1 | G98: 【再放送】今起きているサービス遅延の原因箇所まで、そのままドリルダウンできますか？ ～全トランザクションを常時自動記録し、AI分析で実行中のボトルネックを可視化～ | H98: ワタップ・ジャパン株式会社 | I98: マジセミ株式会社 | J98: Doorkeeper | K98: 不明 | M98: 開発生産性 | N98: AIエージェント | O98: △ | P98: 0 | Q98: 参加者数 | T98: 本セミナーはWebセミナーです ツールはSPEAKERSを使います。URLは直前にメールにてご連絡いたします。 なお、「osslabo.com」「majisemi.com」からのメールが迷惑メールとならないよう、メールの設定をご確認ください。 本セミナーは2026年5月20日に開催されたセミナーの再放送です。 多くのご要望をいただきましたので、再放送の開催が決まりました。 サービス遅延の原因把握が難しくなる背景 クラウド活用やマイクロ | U98: https://majisemi-operation.doorkeeper.jp/events/197891 | W98: 本文一致
A99: 98 | B99: 46218 | C99: 46218 | D99: =MONTH(B99)&"月" | E99: 1 | G99: 【水曜のDX道場】AIが資料を見落とすのはなぜ？ DifyとGeminiで体験する | H99: 水曜のDX道場 | J99: connpass | K99: 会場 | L99: 大阪市北区本庄東１−１８−８ | M99: 生産性向上・業務効率化 | N99: AIエージェント | O99: ◎ | P99: 5 | Q99: 参加者数 | R99: 12 | U99: https://dxdojo.connpass.com/event/400043/ | W99: タイトル一致
A100: 99 | B100: 46218 | C100: 46218 | D100: =MONTH(B100)&"月" | E100: 1 | G100: 【社長限定】いまさら聞けない!ClaudeCode活用術社長がまず使う8つの場面を徹底解説! | H100: 給与アップ研究所セミナー事務局 | J100: こくちーずプロ | K100: オンライン | L100: オンライン 日本 | M100: 営業・マーケ・CS | N100: AIエージェント | O100: ◎ | P100: 1 | Q100: 参加者数 | R100: 100 | T100: 【社長限定】いまさら聞けない！Claude Code活用術 ～社長がまず使う8つの場面を徹底解説～ ━━━━━━━━━━━━━━━━━━ ■開催概要 ━━━━━━━━━━━━━━━━━━ 日時 2026年7月15日（水）12:00～13:00 形式 オンライン（Zoom） 参加費 無料 ━━━━━━━━━━━━━━━━━━ ■こんなお悩みはありませんか？ ━━━━━━━━━━━━━━━━━━ ChatGPTは触ったことがあるけど、その先 | U100: https://www.kokuchpro.com/event/5a90e9ce3378e22b2b7efdec4b2b699d/ | W100: タイトル一致
...

Sheet 参考（AIエージェント明記なし）
A1: 開催日 | B1: セミナー名 | C1: 主催者 | D1: 掲載プラットフォーム | E1: 形式 | F1: テーマ分類 | G1: 集客数 | H1: ソースURL | I1: 概要・抜粋
A2: 46210 | B2: TIS INTEC Group BUSINESS SUMMIT 2026 | C2: TISI株式会社 | D2: ビジネス+IT | E2: online | F2: 営業・マーケ・CS | H2: https://www.sbbit.jp/eventinfo/88822 | I2: 変革の時代。 複雑化する課題の解決に必要なのは、経験と先見性を掛け合わせた幅広い知見と、実用的で先進的な高次元のテクノロジーです。 「TIS INTEC Group BUSINESS SUMMIT」 では、その知見とテクノロジーの融合から生まれた、多角的な支援の事例や技術をご紹介。 ビジネスや課題解決のヒントになるような「発見」にあふれた1日を、ぜひお楽しみください。
A3: 46210 | B3: Zoom CX Summit Tokyo | C3: ZVC JAPAN株式会社 | D3: ビジネス+IT | E3: offline | F3: 営業・マーケ・CS | H3: https://www.sbbit.jp/eventinfo/89152 | I3: 顧客対応は、「問い合わせに答える業務」から、ビジネス成果を生み出す重要な役割へと進化しています。 7月7日に開催する Zoom CX Summit では、AIによる顧客対応の進化、コンタクトセンターの最新トレンド、そして実際の企業による導入・活用事例を通じて、「CXをどう変えれば成果につながるのか」 を具体的にご紹介します。 AI時代の顧客体験を、最新のグローバルトレンド、お客様事例、そしてZoomの最新ソリューションとともにご体感くだ
A4: 46212 | B4: 【オンライン受講】生成AI講座 第4弾 Copilot × Microsoft 365活用講座_第3回 Copilot × PowerPoint — 企画からスライド作成までの高速化 — | D4: Peatix | E4: オンライン | F4: 生産性向上・業務効率化 | H4: https://koukaikouza20260709.peatix.com/ | I4: サブドメインに20260709。Copilot×PowerPoint
A5: 46217 | B5: Beyond Communication 2026 | C5: 株式会社RevComm | D5: ビジネス+IT | E5: offline | F5: 営業・マーケ・CS | H5: https://www.sbbit.jp/eventinfo/88908 | I5: 会話データが導く、次の一手 音声 AI が、営業とサポートに“気づき”を与え、実行までを最短距離でつなぐ。 RevCommは「コミュニケーションを再発明し、人が人を想う社会を創る」という理念のもと、音声AIによって対人コミュニケーションの課題を解決する企業です。 顧客との会話は、企業にとって最も価値ある一次情報です。生成AIの飛躍的な進化により、議事録作成をはじめとする音声AIのビジネス活用は、今まさに本格化しています。 「Beyond
A6: 46218 | B6: 2026年 材料・化学業界の最前線 | D6: Peatix | E6: 不明 | F6: 生産管理・製造・SCM | H6: https://peatix.com/event/5051212 | I6: 2026年7月15日 Industrial AI・スマート製造 デジタルツイン
A7: 46219 | B7: AI and DX Summit | C7: ゾーホージャパン株式会社 | D7: ビジネス+IT | E7: offline | F7: 生産性向上・業務効率化 | H7: https://www.sbbit.jp/eventinfo/89469 | I7: ～学び、つながり、新たなビジネスの可能性に出会う特別な１日～ AI and DX Summitは、AI活用やDX推進をテーマに開催するZoho主催の大型カンファレンスです。 AI、営業改革、業務効率化、顧客体験向上など、企業成長に欠かせないテーマを幅広く取り上げ、最新トレンドや実践事例をご紹介。セッションに加え、展示・交流・個別相談を通じて、AIとDXを“実務にどう活かすか”を体感いただけます。
A8: 46219 | B8: NECが実践するSFA×AIによる営業組織変革 | C8: 株式会社ナレッジワーク | D8: ビジネス+IT | E8: online | F8: 営業・マーケ・CS | H8: https://www.sbbit.jp/eventinfo/89531 | I8: 大手企業の営業責任者・営業企画・DX推進担当者の方に向け、AI商談記録を全社展開するための実践知を共有するセミナーです。 昨今、大手企業では営業組織の規模が大きいゆえに、商談ナレッジの属人化とSFA入力の負荷が同時に課題となっています。過去のナレッジポータルが活用されない、ハイパフォーマーのノウハウが組織展開されないといった問題は、規模が大きいほど顕在化しがちです。さらに、AI商談記録を一部署で導入できても、グループ全体へのガバナンス・
A9: 46219 | B9: 【7/16開催】採用難・属人化に悩むCS担当者必見！インゲージが新機能「AI社員」を活用した次世代の顧客対応ウェビナーを開催 | C9: 株式会社インゲージ | D9: PR TIMES | E9: online | F9: 営業・マーケ・CS | H9: https://prtimes.jp/main/html/rd/p/000000326.000029485.html | I9: コミュニケーションプラットフォーム「Re:lation（リレーション）」を提供し、6,000社以上（※1）の導入実績を誇る株式会社インゲージ（本社：大阪府大阪市、代表取締役社長：和田 哲也）は、2026年7月16日（木）12:00より、無料ウェビナー『Re:lationで叶えるAI社員との共生～効率化の先にある選択肢。新機能「AI社員」がもたらすチームの進化～』を開催することをお知らせいたします。 https://ingage.jp/r
A10: 46219 | B10: 【教室向け】Claude実践セミナー 第3回：AI社員チームで教室運営を自動化する | D10: Peatix | E10: オンライン(Zoom) | F10: 生産性向上・業務効率化 | H10: https://peatix.com/event/5070199 | I10: 2026年7月16日 12:00-13:30 Zoom
A11: 46219 | B11: セールステック・マーケティングDX＆AIカンファレンス 2026 夏 | C11: SBクリエイティブ株式会社（ビジネス＋IT） | D11: ビジネス+IT | E11: online | F11: 営業・マーケ・CS | H11: https://www.sbbit.jp/eventinfo/88526 | I11: 緊迫する世界情勢と原料費の高騰などにより経営環境が不透明な中、多くの企業が生き残りをかけてDXを推進しています。またコロナ禍の影響や長引くインフレによりユーザーの購買行動も変容しており、営業やマーケティングについてもデジタルシフトによる転換が迫られています。さらにはChatGPTをはじめとした生成オープンAIのインパクトが企業のセールス・マーケの形も変えようとしています。変化の時代にセールスとマーケティングはどうDXを進めていくべきでし
A12: 46219 | B12: 製造業のデータ活用・分析セミナー 2026 夏 | C12: SBクリエイティブ株式会社（ビジネス＋IT） | D12: ビジネス+IT | E12: online | F12: 生産管理・製造・SCM | H12: https://www.sbbit.jp/eventinfo/88658 | I12: AI技術の発展により、製造業におけるデータの重要性が急速に高まっています。製造業者は、リアルタイムでデータを収集し、それをAIによって解析・活用する事により、市場の需要に応じた柔軟な生産体制を築きました。その結果、効率性が向上、製品の品質向上やカスタマイズされた製品の提供など、様々な面で競争力を高めることに成功しています。他方では、リアルタイムのセンサーデータと組み合わせ、AIによって解析・活用した、予兆保全や安全確保の取り組みの実現も
A13: 46220 | B13: ものづくりDX&AI フォーラム 2026 夏 東京 | C13: SBクリエイティブ株式会社（ビジネス＋IT） | D13: ビジネス+IT | E13: offline | F13: 生産管理・製造・SCM | H13: https://www.sbbit.jp/eventinfo/88481 | I13: 少子高齢化や地政学リスク増大、国際的な開発競争が激化する中、日本の製造業は新たな転換期を迎えています。日本のものづくり復活のためにもデジタルトランスフォーメーションとAIの活用は、企業の競争力を大きく左右する要素となり、サプライチェーンの再構築や生産効率の向上に不可欠となっています。本フォーラムでは、製造業の未来を切り拓く最前線の事例や技術、AIデジタルツインやロボットによる製造プロセス革新、日本型サプライチェーンの再構築、次世代のスマ
A14: 46226 | B14: SALES AI SUMMIT2026 ー AIで売上を科学する日 ー | C14: FAZOM株式会社 | D14: Peatix | E14: オンライン(Zoom) | F14: 営業・マーケ・CS | H14: https://peatix.com/event/5093762 | I14: 2026年7月23日(木)9:00-17:10 Zoom 無料（主催サイト等で確認）AIと営業データで組織を変えた実践者のみ登壇
A15: 46227 | B15: AIコンテンツ勉強会【AI CONTENTS BOOST #07】AIが「演じる」とき、映像作家は何を創るのか？――アヌシー2026で目撃した映像制作の次なる変化 | D15: Peatix | E15: オンライン | F15: 技術・AI全般 | H15: https://peatix.com/event/5084894 | I15: 2026年7月24日(金)19:00-20:30
A16: 46227 | B16: Coupa Inspire World Tour Tokyo 2026 | C16: Coupa株式会社 | D16: ビジネス+IT | E16: offline | F16: 生産性向上・業務効率化 | H16: https://www.sbbit.jp/eventinfo/89087 | I16: 「Inspire World Tour Tokyo」へようこそ。 Inspireならではの熱気とイノベーションをぜひご体感ください。 本イベントでは、Coupa コミュニティが生み出すネットワーク効果の真価とともに、CoupaのAIネイティブプラットフォームが貴社のビジネスにどのような変革をもたらすかをご提案いたします。 意思決定者の方々を対象とした無料イベントですが、お座席には限りがございます。 ぜひお早めにお申し込みください。
A17: 46227 | B17: KRPフェス2026：生成AIがひらく研究開発と事業創出の可能性〜OpenAIと実践者の視点から考える、AI活用の現在地〜 | C17: 京都リサーチパーク | D17: Peatix | E17: 会場 | F17: 開発生産性 | H17: https://peatix.com/event/5007968 | I17: 2026年7月24日(金)13:30-15:00 OpenAI Japan登壇
A18: 46227 | B18: PendomoniumX Tokyo 2026 | C18: Pendo.io Japan | D18: ビジネス+IT | E18: offline | F18: 営業・マーケ・CS | H18: https://www.sbbit.jp/eventinfo/88335 | I18: AIとともに“判断できる組織”へ 生成AIの進化は、企業にかつてない量と速度でデータを扱う力をもたらしました。しかし競争力を分けるのは、AIを導入したかどうかではありません。データとAIを、経営、プロダクト、顧客体験といった中核領域の意思決定にどう組み込み、組織として機能させられるかです。 PendomoniumX Tokyo 2026では、企業変革を担う経営層およびプロダクトリーダーとともに、AIとデータが実際の意思決定プロセスをどの
A19: 46228 | B19: GWSユーザー必見｜Google AIの最新情報&今後のポジション予測 | C19: 講師:井澤良介(ALLAI/シンカAI) | D19: Peatix | E19: オンライン | F19: 技術・AI全般 | H19: https://miraichi0725.peatix.com/ | I19: Sheets Canvas/Drive プロジェクト実演、ChatGPTとClaudeの違い。チケット販売7/26 22:00まで、サブドメイン0725（年は推定）
A20: 46230 | B20: 【7.27/無料/ｵﾝﾗｲﾝ】AI時代の事業開発の"本質"｜「AI活用」の、その手前にある"全体像" | D20: Peatix | E20: オンライン | F20: 開発生産性 | H20: https://peatix.com/event/5096574 | I20: タイトルに7.27/無料/オンライン（年はイベントID帯から2026年と推定）
A21: 46231 | B21: WorksWay 2026 | C21: 株式会社ワークスアプリケーションズ | D21: ビジネス+IT | E21: online | F21: 生産性向上・業務効率化 | H21: https://www.sbbit.jp/eventinfo/89149 | I21: 人×業務×テクノロジーの再設計で創る新しい企業価値 AIの進化が加速する今、議論はテクノロジーに偏りがちです。 しかし本当に見直すべきなのは、「人」「業務」「テクノロジー」の関係性そのものです。 人の役割を再定義し、業務を再設計し、テクノロジーを組み直す。 三位を一体で捉え直し、その構造を一新する。 単なる効率化ではなく、持続的な競争力を生み出す企業基盤へ。 WorksWay 2026で、その具体解を探ります。
A22: 46231 | B22: 【中堅・大企業向け】AI活用定着の壁、導入したAIはなぜ現場で使われないのか | C22: 株式会社エクサ（協力：マジセミ株式会社） | D22: マジセミ | E22: online | F22: 生産性向上・業務効率化 | G22: 3 | H22: https://prtimes.jp/main/html/rd/p/000005443.000054842.html | I22: ■AI導入は進む一方、活用成果が見えてこない 生成AIやAIツールの導入は、競争力の維持・向上に欠かせない要素として、中堅・大企業を中心に急速に進みつつあります。一方で、導入後に期待したほど業務改善につながらず、現場では一部の社員が個人利用するだけにとどまる、または契約したAIツールが思ったほど使われないといった状況も少なくありません。AIの導入自体をゴールにせず、現場業務の中で継続的に使われ、成果につながる状態をいかに作るかが問われて
A23: 46231 | B23: 【経営者限定5社】AIで次の新規事業をはじめる｜経営者のための2時間ワークショップ | D23: Peatix | E23: 会場 | F23: 生産性向上・業務効率化 | H23: https://peatix.com/event/5077177 | I23: 2026年7月28日16:00-19:00（本編16-18時）経営者限定5社
A24: 46231 | B24: 商談記録の検討・導入で押さえるべき6つの観点 | C24: 株式会社ナレッジワーク | D24: ビジネス+IT | E24: online | F24: 営業・マーケ・CS | H24: https://www.sbbit.jp/eventinfo/89707 | I24: 議事録作成やCRM/SFA入力の自動化を目的に、AI商談記録ツールの導入を検討する企業が増えています。 一方で、「導入したものの議事録作成止まりで、営業力強化やデータ活用にまでつながらない」「対面商談が記録できず、蓄積したデータに抜け漏れがある」といった声も少なくありません。 こうした差が生まれる原因のひとつは、検討段階で文字起こしの精度や議事録作成といった一部の機能だけを比較してしまうことにあります。 商談データを営業組織の資産にする
A25: 46233 | B25: 後継ぎ社長 × AI 業務改革スペシャルイベント | D25: Peatix | E25: 会場 | F25: 生産性向上・業務効率化 | H25: https://peatix.com/event/5037623 | I25: 7月30日 渋谷SOIL 後継ぎ・事業承継期の経営者向け
A26: 46238 | B26: NiCE World Japan 2026 大阪 | C26: ナイスジャパン株式会社 | D26: ビジネス+IT | E26: offline | F26: 営業・マーケ・CS | H26: https://www.sbbit.jp/eventinfo/89511 | I26: NiCE Worldへようこそ NiCE World Japanは、Interactionsで培われた革新性、知見、そしてコミュニティの価値を、さらにスケールアップさせたイベントです。 CXリーダーと共に、最先端テクノロジーを体感し、実際の成果につながるAI戦略を発見してください。 究極のCX体験へ、ぜひご参加ください！
A27: 46239 | B27: AI協奏が拓く人的資本経営の未来 ~HRテクノロジーコンソーシアム 2026年 年次総会~ | C27: HRテクノロジーコンソーシアム | D27: Peatix | E27: 不明 | F27: 生産性向上・業務効率化 | H27: https://hrt-seminar20260805.peatix.com/ | I27: サブドメインhrt-seminar20260805から日付推定（スニペットに日時記載なし）
A28: 46239 | B28: AI組織定着 実践講座 | C28: SBクリエイティブ株式会社/ビジネス+IT | D28: ビジネス+IT | E28: online | F28: 営業・マーケ・CS | H28: https://www.sbbit.jp/eventinfo/89680 | I28: 日時： 2026年8月5日（水）16:00～18:00 会場： オンライン 定員： オンライン受講 無制限 受講料：オンライン受講 22,000円（税込） 主催： SBクリエイティブ株式会社（ビジネス＋IT／FinTech Journal）
A29: 46240 | B29: AI音声DX最前線 | C29: SBクリエイティブ株式会社（ビジネス＋IT） | D29: ビジネス+IT | E29: online | F29: 生産性向上・業務効率化 | H29: https://www.sbbit.jp/eventinfo/89285 | I29: 営業・接客・コンタクトセンターなど、企業の最前線となる“現場コミュニケーション”では、商談記録の属人化、対応品質のばらつき、不適切対応や情報隠蔽、カスタマーハラスメント対応など、可視化されにくい課題が顕在化しています。特に対面・電話でのやり取りは記録が残りづらく、教育・監査・ナレッジ共有・証跡管理の観点でも大きな課題となってきました。こうした中、AI音声技術の進化により、会話の自動文字起こし、要約、感情分析、リアルタイム支援、データ連携
A30: 46240 | B30: LSS×Dell Technologies 【AI PC時代の業務変革最前線】最新の生成AI活用支援プログラムと業界別AIソリューションユースケースセミナー | C30: LSS×Dell Technologies | D30: Peatix | E30: 会場 | F30: 営業・マーケ・CS | H30: https://peatix.com/event/4760653 | I30: 2026年8月6日(木)15:00-19:00 申込締切8/5
A31: 46240 | B31: NiCE World Japan 2026 福岡 | C31: ナイスジャパン株式会社 | D31: ビジネス+IT | E31: offline | F31: 営業・マーケ・CS | H31: https://www.sbbit.jp/eventinfo/89512 | I31: NiCE Worldへようこそ NiCE World Japanは、Interactionsで培われた革新性、知見、そしてコミュニティの価値を、さらにスケールアップさせたイベントです。 CXリーダーと共に、最先端テクノロジーを体感し、実際の成果につながるAI戦略を発見してください。 究極のCX体験へ、ぜひご参加ください！
A32: 46240 | B32: XR Kaigi Hub 名古屋 - フィジカルAI meets XR | D32: Peatix | E32: 会場 | F32: 生産管理・製造・SCM | H32: https://xrkaigihub-nagoya2026.peatix.com/view | I32: 2026年8月6日11:00-18:00 STATION Ai
A33: 46242 | B33: MERGE 2026 - AI駆動開発 × Design | C33: GustoDevelopment/Protocore/AI駆動開発コミュニティ/Next AI Leaders | D33: Peatix | E33: ハイブリッド | F33: 開発生産性 | H33: https://merge2026.peatix.com/view | I33: 2026年8月8日(土)10:00-20:00 会場200名+オンライン300名想定
A34: 46254 | B34: 8/20（木）第1回コアコネ超会議 | D34: Peatix | E34: 会場 | F34: 生産性向上・業務効率化 | H34: https://peatix.com/event/5073918 | I34: 2026年8月20日19:00-21:30 テーマ「AI爆速成長時代のベンチャー経営の手引き」コア会員無料/一般5,000円
A35: 46254 | B35: AI時代の製造現場DX成功の要因 | C35: SBクリエイティブ株式会社（ビジネス＋IT） | D35: ビジネス+IT | E35: online | F35: 生産管理・製造・SCM | H35: https://www.sbbit.jp/eventinfo/88939 | I35: 少子高齢化による労働人口の減少や働き手の高齢化により、製造業では「人材不足」や「技能伝承」といった長年懸念されている問題が一段と深刻化しています。これらの課題を解決するためにはDXに加え、生成AIやフィジカルAI・ロボティクスの活用が急務とされています。「情報の見える化」「技術継承支援」「DX・AI人材の育成」「生産性の向上」など、今後急務且つ、長期的に取り組む必要のある事が山積みです。当Webセミナーでは、先進的な取り組みで、製造業の
A36: 46258 | B36: Microsoft Copilotビジネス実践講座第2弾 | C36: SBクリエイティブ株式会社（ビジネス＋IT） | D36: ビジネス+IT | E36: hybrid | F36: 生産性向上・業務効率化 | H36: https://www.sbbit.jp/eventinfo/89968 | I36: 日時： 2026年8月24日（月）15:00 - 18:00 会場： 住友不動産虎ノ門タワー23F（SBクリエイティブ株式会社） 定員： 会場 30名程度 ／ オンライン受講 無制限 受講料： 会場受講 33,000円（税込） ／ オンライン受講 22,000円（税込） 主催： SBクリエイティブ株式会社（ビジネス＋IT）
A37: 46259 | B37: AIが自律的に事業リスクを見つけ、打ち手まで示す経営へ | C37: 日本オラクル株式会社 | D37: ビジネス+IT | E37: online | F37: 生産性向上・業務効率化 | H37: https://www.sbbit.jp/eventinfo/89893 | I37: 業績悪化の兆候、需要の変化、供給遅延、コスト超過、人材流出のリスク。 ビジネス上の重要な変化は、顕在化する前から、企業内のデータや業務プロセスに現れています。 これからのAIに求められるのは、質問に答えることだけではありません。企業固有のデータ、ビジネスルール、業務の流れを理解し、異常やリスクを自律的に検知する。さらに、その背景や影響を分析し、判断の根拠となるエビデンスとともに、次に取るべきアクションを提示することです。 Oracle
A38: 46260 | B38: 【B-5】仕事に役立つ、生成AIを活用した広報7つのコツ講座。 | D38: Peatix | E38: 会場 | F38: 生産性向上・業務効率化 | H38: https://peatix.com/event/5013999 | I38: 2026年8月26日(水)11:00-13:00 生成AIを広報業務に活かす7つの視点、プレスリリース下書き・チェックリスト持ち帰り
A39: 46260 | B39: 検索・要約で終わらせない、Copilotでつくる「AI社員」実践ワークショップを8月26日に無料オンライン開催 | C39: 株式会社Meta Heroes | D39: PR TIMES | E39: online | F39: 生産性向上・業務効率化 | H39: https://prtimes.jp/main/html/rd/p/000000403.000094539.html | I39: 株式会社Meta Heroesと株式会社Meta Osakaは、2026年8月26日（水）15:00〜17:00、企業の実務担当者を対象とした無料オンラインイベント「Copilotでつくる『AI社員』実践ワークショップ」をGoogle Meetで開催します。 本イベントでいう「AI社員」は、AIが人間の社員と同じように完全自律で働くことを意味するものではありません。メール、資料作成、情報整理などの日常業務を支援するAI活用の考え方を示す
A40: 46261 | B40: 【見逃しアーカイブ】Gemini × NotebookLMで「26人のAI社員」を雇って仕事を自動化 完全攻略セミナー | C40: えーたん(@ai_jitan) | D40: Peatix | E40: アーカイブ配信 | F40: 生産性向上・業務効率化 | H40: https://peatix.com/event/5156216 | I40: 見逃しアーカイブ 8月27日〜31日限定販売
A41: 46262 | B41: THE MARKETING SHIFT 2026 in TOKYO / REHATCH株式会社 | C41: REHATCH株式会社 | D41: Peatix | E41: 会場+オンライン | F41: 生産管理・製造・SCM | H41: https://peatix.com/event/5112256 | I41: 2026年8月28日(金)18:30-22:00（PR TIMES等で確認）経営者・CMO・マーケター向け、マーケティングAI OS「ENSOR」正式リリース、無料
A42: 46266 | B42: 【国内外の大手企業トップリーダーが集結】三菱UFJ・NTTデータ・フジクラ・Google・外資系コンサルなど語る、AI時代の「勝ち組の条件」 | C42: 日経BP | D42: Peatix | E42: ハイブリッド | F42: 技術・AI全般 | H42: https://peatix.com/event/5142487 | I42: AIリーダーズ会議 2026 Autumn。9月1日9:30-18:10・2日9:30-17:40、無料事前登録（日経BP等の告知で確認）
A43: 46267 | B43: 【好評につき再放送】NECが実践するSFA×AIによる営業組織変革 | C43: 株式会社ナレッジワーク | D43: ビジネス+IT | E43: online | F43: 営業・マーケ・CS | H43: https://www.sbbit.jp/eventinfo/90088 | I43: 大手企業の営業組織では、SFAの入力負荷や商談ナレッジの属人化が長年の課題となっています。特に組織規模が大きいほど、ハイパフォーマーのノウハウが組織全体に広がらず、PoC（概念実証）から全社展開へのロードマップが描けないといった壁に直面しがちです。 NECデジタルワークプレイス統括部では、SFAとAI商談記録を連携させ、1,000名規模での全社展開に向けた取り組みを推進しています。 AI商談記録の導入により、1会議あたり約25分の工数削
A44: 46268 | B44: AI時代の設計・製造・全体最適を実現する DX戦略セミナー | C44: SBクリエイティブ株式会社（ビジネス＋IT） | D44: ビジネス+IT | E44: offline | F44: 生産管理・製造・SCM | H44: https://www.sbbit.jp/eventinfo/89872 | I44: 本セミナーでは、「2026年版ものづくり白書」を手掛かりに、日本の製造業が直面する人手不足や不確実性、生産性向上ニーズにどう向き合うかを整理します。 政策動向と先進企業事例を踏まえ、設計から製造・経営までをつなぐデータ基盤、AI・生成AI活用、経済安全保障対応を含むDX戦略と具体的な実践シナリオを提示し、持続的成長と競争力強化への道筋を示します。
A45: 46268 | B45: SAP Transformation Excellence Tour Osaka | C45: SAPジャパン株式会社 | D45: ビジネス+IT | E45: offline | F45: 生産性向上・業務効率化 | H45: https://www.sbbit.jp/eventinfo/89844 | I45: ビジネス変革を成功させるには、実行可能な戦略、ビジネスとITの統一されたビジョン、そして具体的な成果の創出への注力が必要です。SAP Transformation Excellence Tour Osakaでは、ビジネス変革の成功における、新たな視点を提示します。 プロセスエクセレンス、エンタープライズアーキテクチャ、デジタルアドプションを組み合わせ、真に包括的かつ継続的なビジネス変革を実現する革新的な方法についてご提案します。ビジネス
A46: 46272 | B46: その生成AI、「効率化」だけに使っていませんか。——組織で「自分たちの答え」を生み出す使い方を、複雑系研究30年・田原真人と考える【企業の人材開発・組織開発・新規事業の方へ｜無料オンライン60分】 | C46: 岸本渉(Oxymoron) | D46: Peatix | E46: オンライン(Zoom) | F46: 生産性向上・業務効率化 | H46: https://peatix.com/event/5149893 | I46: 2026年9月7日(月)19:00-20:00 Zoom 無料 定員50名
A47: 46273 | B47: 生成AIサミット Vol.8 〜業務効率化の「その先」へ：生成AIで切り開くビジネスの未来〜 | D47: Peatix | E47: 不明 | F47: 生産性向上・業務効率化 | H47: https://peatix.com/event/4918327 | I47: 2026年9月8-9日 生成AIを社内生産性ツールから事業変革へ
A48: 46274 | B48: 【9/9(水)開催】AIの深化と科学への応用へ。AI-Science Nexusセンター（AISNeC）設立シンポジウム開催のご案内 | C48: 東京科学大学 AISNeC | D48: Peatix | E48: 会場 | F48: 営業・マーケ・CS | H48: https://peatix.com/event/5078782 | I48: 2026年9月9日(水)13:00-17:10 懇親会17:30-19:30
A49: 46275 | B49: WalkMe on Tour Tokyo 2026 | C49: WalkMe株式会社 | D49: ビジネス+IT | E49: offline | F49: 生産性向上・業務効率化 | H49: https://www.sbbit.jp/eventinfo/89612 | I49: 生成AIに大きな価値を期待するCIOは95%にのぼる一方、AIを使いこなして業務を大きく変革できている従業員はわずか8%にとどまります。 背景には、多くのAIが業務の文脈を読み取れず、アプリケーションを横断できず、実際の業務を実行できず、成果を証明できない課題があります。 WalkMeは、企業のAI活用を成功に導く不可欠なレイヤーとして、リアルタイムの文脈とアプリ横断の実行力を与え、AI投資を確かな成果に変えるAIアダプションを実現しま
A50: 46276 | B50: NiCE World Tokyo 2026 | C50: ナイスジャパン株式会社 | D50: ビジネス+IT | E50: offline | F50: 営業・マーケ・CS | H50: https://www.sbbit.jp/eventinfo/90023 | I50: NiCE World Tokyoは、Interactionsで培われた革新性、知見、そしてコミュニティの価値を、さらにスケールアップさせたイベントです。 CXリーダーと共に、最先端テクノロジーを体感し、実際の成果につながるAI戦略を発見してください。 究極のCX体験へ、ぜひご参加ください！ NiCE World Tokyo 2026では、あらゆるセッションや体験が、新たな発想と実践的な成果につながるよう設計されています。日本各地で開催さ
A51: 46276 | B51: Salesforceを”使うだけ”から”成果を出す”へ | C51: 日本アイ・ビー・エム株式会社 | D51: ビジネス+IT | E51: online | F51: 営業・マーケ・CS | H51: https://www.sbbit.jp/eventinfo/89838 | I51: AI活用への関心が高まる一方で、「何から着手すべきかわからない」「PoCで止まってしまい業務成果につながらない」「Salesforceを導入していても十分に使いこなせていない」といった課題を抱える企業は少なくありません。特に営業・顧客対応・業務オペレーションの現場では、限られた人員の中で生産性向上とROI最大化の両立が求められており、AIをどう業務に組み込み、実行・定着させるかが重要なテーマになっています。 本セミナーでは、IBMがどの
A52: 46279 | B52: Anaplan Connect Tokyo 2026 | C52: Anaplan ジャパン株式会社 | D52: ビジネス+IT | E52: offline | F52: 営業・マーケ・CS | H52: https://www.sbbit.jp/eventinfo/89804 | I52: 急速に変化する市場環境やサプライチェーンの不確実性により、従来の計画手法では迅速な意思決定が難しくなっています。部門間の連携不足やデータの分断が、成長機会の損失につながっています。 多くの企業が同じ悩みを抱えています。売上予測や需給計画の精度に限界を感じ、経営資源の最適配分やリスクに備えた柔軟な対応に不安を持つのは決して一社だけではありません。 先進企業の導入事例や専門家の洞察を通じて、AIを活用したシナリオ プランニングが意思決定をど
A53: 46281 | B53: PERSOL AI CONFERENCE 2026 | C53: パーソルホールディングス株式会社 | D53: ビジネス+IT | E53: online | F53: 営業・マーケ・CS | H53: https://www.sbbit.jp/eventinfo/89954 | I53: AI活用は、現場での試行から全社戦略へ。 投資判断や業務再設計、人材育成、そして組織づくりまで、あらゆるレイヤーでAIを前提とした意思決定が求められる時代に入りました。 本カンファレンスでは、有識者や企業変革の最前線に立つCXOの視点から、AX時代に求められる意思決定と実践のヒントを探ります。 AIは単なる業務効率化のツールから、経営の意思決定・事業モデル・顧客価値そのものを再定義する力へと進化しました。いま企業に求められるのは「AI人
A54: 46281 | B54: 企業内エージェンティックAI基盤構築実践講座 | C54: SBクリエイティブ株式会社（ビジネス＋IT） | D54: ビジネス+IT | E54: hybrid | F54: 生産性向上・業務効率化 | H54: https://www.sbbit.jp/eventinfo/89962 | I54: 日時： 2026年9月16日(水)15:00～18:00 会場： 住友不動産虎ノ門タワー23F（SBクリエイティブ株式会社） 定員： 会場 30名程度 ／ オンライン受講 無制限 受講料： 会場受講 33,000円（税込） ／ オンライン受講 22,000円（税込） 主催： SBクリエイティブ株式会社（ビジネス＋IT）
A55: 46282 | B55: Seizo Trend 製造DX&AI-DAY ＠Industry Forum 2026 秋 | C55: SBクリエイティブ株式会社（ビジネス＋IT） | D55: ビジネス+IT | E55: online | F55: 生産管理・製造・SCM | H55: https://www.sbbit.jp/eventinfo/89590 | I55: 緊迫する世界情勢による資源高、長引くインフレは日本経済を直撃しています。長らく日本経済を牽引してきた製造業は、国際競争の激化、サプライチェーンのリスク、デジタル化の遅れ、カーボンニュートラル対応など新たな課題などに成長を阻まれ、競争力を失いつつあります。日本のものづくりは現場熟練工や独自製造技術による個別最適の強みを持ちながら、データの活用やデジタル標準化の部分で遅れをとっており、製造DXによるサプライチェーンの強靭化やデジタルによる新
A56: 46282 | B56: Zendesk Showcase Tokyo 2026 | C56: 合同会社Zendesk | D56: ビジネス+IT | E56: offline | F56: 営業・マーケ・CS | H56: https://www.sbbit.jp/eventinfo/89878 | I56: 今年のShowcase Tokyoは、ユースケースのショーケース（発表会）と言うべきプログラムを満載してお届けいたします。過去最大数のお客様事例を目玉としながら、最新機能のご紹介、使い方をご自分のものにしていただくワークショップといった具体的な内容を通して、貴社のCX/EX戦略や、現場の利用シーンに直接お役立ていただける、濃厚な持ち帰りのある場を目指しています。 顧客体験（CX）・従業員体験（EX）に特化したZendeskのAIとは何物
A57: 46283 | B57: ついに始まったChatGPT広告 有効な運用、AIO・コンテンツ対策から検証（開始は18:30です！） | D57: Peatix | E57: 会場+オンライン | F57: 営業・マーケ・CS | H57: https://peatix.com/event/5137202 | I57: 2026年9月18日(金)18:30 会場・オンライン参加
A58: 46286 | B58: 動画生成AIの今とこれから 〜STUDIO異次元が語る活用動向と、海外で感じたAI事情〜 | D58: Peatix | E58: オンライン(Zoom) | F58: 技術・AI全般 | H58: https://peatix.com/event/5174714 | I58: 2026年9月21日(月)21:00-22:00 Zoom
A59: 46289 | B59: なぜ、AI活用だけでは製造業の開発期間を短縮できないのか？ | C59: SCSK株式会社（協力：マジセミ株式会社） | D59: マジセミ | E59: online | F59: 生産管理・製造・SCM | G59: 0 | H59: https://prtimes.jp/main/html/rd/p/000005647.000054842.html | I59: ■ 製造業で求められる開発期間の短縮 市場ニーズの多様化や製品ライフサイクルの短期化を背景に、製造業では設計・開発期間のさらなる短縮が求められています。こうした中、後工程での手戻りを抑えるため、CAEをはじめとするデジタル技術を活用し、設計・開発の早い段階から性能や品質、製造性を検討・検証する「フロントローディング」の重要性が高まっています。 一方で、上流工程で高度な検討・検証を行うには、専門的な知識やスキルが求められる場面も少なくあり
A60: 46291 | B60: 9月26日(土)ITコーディネータ京都 経営セミナー：AIで伸びる会社、止まる会社 ― その差は社長の関与にある | C60: ITコーディネータ京都 | D60: Peatix | E60: ハイブリッド | F60: 生産性向上・業務効率化 | H60: https://peatix.com/event/5114140 | I60: 2026年9月26日(土)14:00-16:00 無料
A61: 46291 | B61: 【京都橘大学】公開講座「生成AI✕著作権 ─アニメの現場を参考に「声の著作権」を考える－【申込みチケット】 | C61: 京都橘大学 | D61: Peatix | E61: 会場 | F61: 技術・AI全般 | H61: https://peatix.com/event/5116346 | I61: 2026年9月26日(土)13:20-15:00
A62: 46293 | B62: 【Manufacturing Innovation】 世界のロボット技術を地域産業へ―自動化・省人化から考える海外企業との共創― | C62: Invest in Aichi-Nagoya Acceleration Initiative | D62: Peatix | E62: 会場 | F62: 生産管理・製造・SCM | H62: https://peatix.com/event/5114821 | I62: 2026年9月28日(月)15:00-16:15
A63: 46295 | B63: AI活用で年間200万円節約！人材系SaaS内製化の進め方【無料オンラインセミナー】 | D63: Peatix | E63: オンライン | F63: 生産性向上・業務効率化 | H63: https://peatix.com/event/5190409 | I63: 2026年9月30日12:00-12:45 オンライン無料 中小・中堅企業の経営者・管理部門向け
